{
    "version": "https://jsonfeed.org/version/1",
    "title": "Sneexy的神奇口袋",
    "subtitle": "",
    "icon": "https://sneexy.github.io/images/favicon.ico",
    "description": "热爱可抵岁月漫长",
    "home_page_url": "https://sneexy.github.io",
    "items": [
        {
            "id": "https://sneexy.github.io/2022/09/29/coding/%E8%A7%A3%E5%86%B3%E6%99%BA%E8%83%BD%E6%8C%87%E9%92%88%E7%9B%B8%E4%BA%92%E5%BC%95%E7%94%A8%E5%AF%BC%E8%87%B4%E7%9A%84%E5%86%85%E5%AD%98%E6%B3%84%E9%9C%B2/",
            "url": "https://sneexy.github.io/2022/09/29/coding/%E8%A7%A3%E5%86%B3%E6%99%BA%E8%83%BD%E6%8C%87%E9%92%88%E7%9B%B8%E4%BA%92%E5%BC%95%E7%94%A8%E5%AF%BC%E8%87%B4%E7%9A%84%E5%86%85%E5%AD%98%E6%B3%84%E9%9C%B2/",
            "title": "解决智能指针相互引用导致的内存泄露",
            "date_published": "2022-09-28T18:01:57.000Z",
            "content_html": "<h1 id=\"解决智能指针相互引用导致的内存泄露\"><a class=\"anchor\" href=\"#解决智能指针相互引用导致的内存泄露\">#</a> 解决智能指针相互引用导致的内存泄露</h1>\n<h2 id=\"问题描述\"><a class=\"anchor\" href=\"#问题描述\">#</a> 问题描述</h2>\n<p>智能指针相互持有时会造成内存泄露。智能指针和普通指针相互持有也是。</p>\n<p>一般出现在共享指针（shared_ptr）之间，或者共享指针和普通指针（xxx *）之间。</p>\n<h2 id=\"解决办法\"><a class=\"anchor\" href=\"#解决办法\">#</a> 解决办法</h2>\n<p>如果是共享指针之间相互持有：将其中一个改为 weak_ptr。</p>\n<p>如果是共享指针和普通指针相互持有：将普通指针改为 weak_ptr。</p>\n<h3 id=\"weak_ptr如何操作\"><a class=\"anchor\" href=\"#weak_ptr如何操作\">#</a> weak_ptr 如何操作</h3>\n<p>weak_ptr 没有重载 <code>operator-&gt;</code>  和 <code>operator *</code>  操作符，因此不可直接通过 weak_ptr 使用对象。</p>\n<p>使用方法<sup class=\"footnote-ref\"><a href=\"#fn1\" id=\"fnref1\">[1]</a></sup>：</p>\n<pre><code>shared_ptr&lt;int&gt; ptr = make_shared&lt;int&gt;(10); \nweak_ptr&lt;int&gt; ptr1 = ptr; // 必须使用shared_ptr初始化weak_ptr  \nshared_ptr&lt;int&gt; ptr2 = ptr1.lock(); // 利用返回的shared_ptr初始化\n</code></pre>\n<h3 id=\"weak_ptr中构造函数使用了this\"><a class=\"anchor\" href=\"#weak_ptr中构造函数使用了this\">#</a> weak_ptr 中构造函数使用了 this</h3>\n<p>weak_ptr 指向的对象，其类的构造函数中不能使用 <code>this</code> ，需要使用 <code>shared_from_this()</code>  来代替。原因是：智能指针在构造函数执行完毕后生成，此时还不存在引用计数指针。</p>\n<p><code>shared_from_this()</code>  的使用方法为，以 EnableSharedPtr 类为例<sup class=\"footnote-ref\"><a href=\"#fn2\" id=\"fnref2\">[2]</a></sup>：</p>\n<ol>\n<li>使 <code>EnableSharedPtr</code>  类继承自 <code>std::enable_shared_from_this&lt;EnableSharedPtr&gt;</code></li>\n<li>将 <code>this</code>  直接替换为 <code>shared_from_this()</code> 。</li>\n<li>这一点是构造函数中特有的：需要在构造函数完成后再调用含有 <code>shared_from_this()</code>  的函数（例如<sup class=\"footnote-ref\"><a href=\"#fn2\" id=\"fnref2:1\">[2:1]</a></sup>中的 <code>GetObject()</code> ）为对应变量真正赋值。</li>\n</ol>\n<h3 id=\"附一些看过的帖子\"><a class=\"anchor\" href=\"#附一些看过的帖子\">#</a> 附：一些看过的帖子</h3>\n<p>有助于了解，不一定用上了</p>\n<ul>\n<li>\n<p><span class=\"exturl\" data-url=\"aHR0cHM6Ly9xYS4xcjFnLmNvbS9zZi9hc2svMzUyMjI4OTAxMS8=\">即使正确使用 make_shared,shared_from_this () 也会导致 std :: bad_weak_ptr | (1r1g.com)</span></p>\n</li>\n<li>\n<p><span class=\"exturl\" data-url=\"aHR0cHM6Ly96aGlxaWFuZy5vcmcvY29kaW5nL3N0ZC1tYWtlLXNoYXJlZC1lbmFibGUtc2hhcmVkLWZyb20tdGhpcy5odG1s\">智能指针的辅助函数 std::make_shared 和 std::enable_shared_from_this - 阅微堂 (zhiqiang.org)</span></p>\n</li>\n<li>\n<p><span class=\"exturl\" data-url=\"aHR0cHM6Ly93ZW5rdS5iYWlkdS5jb20vdmlldy85MzJmOTkzMDE3NzkxNzExY2M3OTMxYjc2NWNlMDUwODc2MzI3NTMyLmh0bWw=\">C++ 智能指针的正确使用方式 - 百度文库 (baidu.com)</span></p>\n</li>\n<li>\n<p><span class=\"exturl\" data-url=\"aHR0cHM6Ly9ibG9nLmNzZG4ubmV0L2dldHRvZ2V0dG8vYXJ0aWNsZS9kZXRhaWxzLzYwMzIxNTY2\">weak_ptr 与 shared_ptr_gettogetto 的博客 - CSDN 博客</span></p>\n</li>\n<li>\n<p><span class=\"exturl\" data-url=\"aHR0cHM6Ly9ibG9nLmNzZG4ubmV0L2x4aF9fX19fL2FydGljbGUvZGV0YWlscy8xMjA2OTk1MjA=\">OC 内存泄漏_Titanium、的博客 - CSDN 博客_oc 内存泄漏</span></p>\n</li>\n<li>\n<p><span class=\"exturl\" data-url=\"aHR0cHM6Ly9ibG9nLmNzZG4ubmV0L20wXzUxOTU1NDcwL2FydGljbGUvZGV0YWlscy8xMTgwNzUzODQ=\">[C++11] shared_ptr 使用的注意事项 (内存被重复析构，内存泄漏问题)_唐火的博客 - CSDN 博客_指针重复析构</span></p>\n</li>\n<li>\n<p><span class=\"exturl\" data-url=\"aHR0cHM6Ly9ibG9nLmNzZG4ubmV0L3dlaXhpbl80NjE2ODA1NC9hcnRpY2xlL2RldGFpbHMvMTE5NTE1MjM5\">shared_ptr 共享指针的陷阱，交叉引用导致内存泄漏_过往山海的博客 - CSDN 博客_共享指针内存泄漏</span></p>\n</li>\n<li>\n<p><span class=\"exturl\" data-url=\"aHR0cHM6Ly93d3cub3Jjb2RlLmNvbS9xdWVzdGlvbi8yNTA4MDlfazkzMGUyLmh0bWw=\">使用指南：共享指针与普通指针 - 或代码 (orcode.com)</span></p>\n</li>\n</ul>\n<hr class=\"footnotes-sep\" />\n<section class=\"footnotes\">\n<ol class=\"footnotes-list\">\n<li id=\"fn1\" class=\"footnote-item\"><p><span class=\"exturl\" data-url=\"aHR0cHM6Ly9ibG9nLmNzZG4ubmV0L3dlaXhpbl80NTU5MDQ3My9hcnRpY2xlL2RldGFpbHMvMTEzMDU3NTQ1\">弱类型指针 weak_ptr 的使用 (详解)_肥肥胖胖是太阳的博客 - CSDN 博客_weak_ptr 使用</span> <a href=\"#fnref1\" class=\"footnote-backref\">↩︎</a></p>\n</li>\n<li id=\"fn2\" class=\"footnote-item\"><p><span class=\"exturl\" data-url=\"aHR0cHM6Ly9ibG9nLmNzZG4ubmV0L3dlaXhpbl80NDUxNzY1Ni9hcnRpY2xlL2RldGFpbHMvMTE0MTk1MjY1\">智能指针之与 shared_ptr 有关的 enable_shared_from_this 类模板 04_Mango 酱的博客 - CSDN 博客</span> <a href=\"#fnref2\" class=\"footnote-backref\">↩︎</a> <a href=\"#fnref2:1\" class=\"footnote-backref\">↩︎</a></p>\n</li>\n</ol>\n</section>\n",
            "tags": [
                "编程",
                "C++",
                "OC",
                "编程"
            ]
        },
        {
            "id": "https://sneexy.github.io/2022/09/25/drama/%E5%B9%BF%E6%92%AD%E5%89%A7%E5%8D%95%E6%9C%9F%E5%89%A7%E8%AF%84/",
            "url": "https://sneexy.github.io/2022/09/25/drama/%E5%B9%BF%E6%92%AD%E5%89%A7%E5%8D%95%E6%9C%9F%E5%89%A7%E8%AF%84/",
            "title": "广播剧单期剧评",
            "date_published": "2022-09-24T16:30:52.000Z",
            "content_html": "<h1 id=\"广播剧单期剧评\"><a class=\"anchor\" href=\"#广播剧单期剧评\">#</a> 广播剧单期剧评</h1>\n<p>注：非全一期的广播剧。剧评也可能包含几期一起。</p>\n<p>注：可能涉及剧透</p>\n<details class=\"success\"><summary>《营销号说你喜欢我 第一季》DK（役周秋隼）X 冬冬（役司镜若）</summary><div>\n<p><strong>第一、二期</strong></p>\n<ul>\n<li>冬冬的受音诶，这个声线我喜欢。有气质，不过内心 OS 是另一种风格，或委屈或搞笑或咆哮体，反差萌。冬冬的演技好好哦，很多情绪都拿捏得到位。</li>\n<li>剧的后期也不错。</li>\n</ul>\n<p><strong>第三期</strong></p>\n<ul>\n<li>这一期周秋隼多少有点油腻了喔。司镜若，能屈能伸，就是脑子慢半拍。</li>\n<li>戏中戏里 DK 好 A，冬冬也是清冷路线，挺好的</li>\n<li>碎嘴八卦他们俩有一腿的工作人员，有点不适</li>\n</ul>\n<p><strong>第四期</strong></p>\n<ul>\n<li>这一期比较平，周秋隼这莫名其妙地倒贴得有点严重。（不过弹幕剧透了原因</li>\n<li>直球克傲娇</li>\n</ul>\n<p><strong>第五期</strong></p>\n<ul>\n<li>\n<p>戏中戏冬冬配女儿，娇娇的。</p>\n</li>\n<li>\n<p>哦哟，冬冬的气息戏，司镜若这儿 OS 后说出来的话感觉欲拒还迎了。周秋隼真不把自己当外人！</p>\n</li>\n</ul>\n<p><strong>第六期</strong></p>\n<ul>\n<li>13'。喂饭那段比较搞笑，特别是内心 OS“撑死你撑死你……” 那句。</li>\n<li>揭开了一些剧院往事，司镜若和董晓伟的伤疤。（看弹幕才知道董晓伟的 CV 是郭浩然，又配了一个瘦音胖子哈哈，不怪司镜若说董看起来 120 斤，这听起来也只有 120 斤）<br />\n不过他一直执着于即使牺牲重要的东西（比如感情）也要挽救剧院，另一边也这样要求司镜若，有点执念太深吧，毕竟人更重要。</li>\n</ul>\n<p><strong>第七、八期</strong></p>\n<ul>\n<li>\n<p>第 7 期过渡一下。</p>\n</li>\n<li>\n<p>第 8 期的戏中戏表现得太好了，一直到杀青出不了戏。冬冬演技真好，两个角色都很有代入感。</p>\n</li>\n<li>\n<p>后期优秀</p>\n</li>\n</ul>\n<p><strong>第九、十期</strong></p>\n<ul>\n<li>完结了，这两期司镜若老是装傻。收尾也有些仓促了，停在安戚的故事上。就从安戚这两期的戏份来看，也不完全是坏人，反而司镜若他爸清高得不切实际，行为又没有跟上。</li>\n</ul>\n<p><strong>各种花絮、戏中戏《烽火》未播片段</strong></p>\n<ul>\n<li>\n<p>这部剧的售后服务很饱满诶。戏中戏挺好的，中秋番外里 DK 的难过但不能崩溃的脆弱感不错，七夕的录屏和春节的沙雕，冬冬喊 “哥哥” 的合集太撒娇了</p>\n</li>\n<li>\n<p>导演用心了，花絮中的几个片段剧中确实能感受到，完成度很高。让小孩儿配音确实比很多夹着嗓子配的自然。</p>\n</li>\n<li>\n<p>再次表白冬冬的配音，受音太香了。其他 CV 也都挺好的</p>\n</li>\n</ul>\n</div></details>\n<details class=\"success\"><summary>《无耻之徒》斑马（役姜晓宁）X 笑意（役韩嘉）</summary><div>\n<p><strong>第一期</strong></p>\n<ul>\n<li>\n<p>千呼万唤始出来，从《不法之徒》就很喜欢韩嘉，《无耻之徒》原作 n 刷了。</p>\n</li>\n<li>\n<p>五年后的姜晓宁，看文的时候觉得是比较沉闷阴郁、玩世不恭、怀着执念的瘦子，感觉有点活泼了。不过毕竟是年下，一直比韩嘉天真。<br />\n五年前的姜晓宁，又毛躁又脆弱，比较符合。</p>\n</li>\n<li>\n<p>韩嘉的声音好听，不过没有《不法之徒》那么惊艳，傲劲儿收敛了一些，有些温柔了。美人儿～</p>\n</li>\n</ul>\n</div></details>\n<details class=\"success\"><summary>《大力出奇迹》夙七烈 X 冬冬</summary><div>\n<p><strong>第一期</strong></p>\n<ul>\n<li>比较搞笑，不按套路出牌。不过冬冬是攻音，战斗力爆表了。</li>\n</ul>\n</div></details>\n<details class=\"success\"><summary>《08321》贾诩、林予曦、倒吊男 X 冬冬、刘明月、李兰陵</summary><div>\n<p><strong>声展 &amp; 第一期</strong></p>\n<ul>\n<li>不知道哪里 mark 来的，还是高优先级。应该是群像搞笑剧。</li>\n<li>冬冬的声展（役陈逸）循环了很多遍，这个声音，我的何故又回来了，比何故声线更高冷一点，很好听。贾诩（役李嘉豪）江西方言，听不懂，但搞笑。还是分不清李兰陵和锦鲤和斑马，刘明月也一股羊味儿，听少了</li>\n</ul>\n<p><strong>第 2-5 期 &amp; 小剧场 1-2</strong></p>\n<ul>\n<li>很难不怀疑是声优定制，人设分明，有梗，不过老是分不出黄博文（CV 刘明月），封面要是按出场的两两放一块儿可能容易识别一点。赵明泽（CV 林予曦）人设到底是花花公子还是纯情少年😂？</li>\n<li>小剧场里贾诩读诗很好听，气质（反差萌？</li>\n</ul>\n<p><strong>小剧场 3</strong></p>\n<ul>\n<li>冬冬的青受音我好爱</li>\n</ul>\n</div></details>\n<details class=\"success\"><summary>《骑士的情书》擎苍 X 矜持ING</summary><div>\n<p><strong>第九期</strong></p>\n<ul>\n<li>袁瑞真是傻得可爱。委屈巴巴。郑秋阳也直得搞笑</li>\n<li>震惊，在这里也能听到小 C。柏图 29’（就两句话）</li>\n</ul>\n</div></details>\n<details class=\"success\"><summary>《爷们儿》Holynight（役严肆）X陈小C（役乔已）</summary><div>\n<p><strong>第一期</strong></p>\n<ul>\n<li>小 C 役舞蹈教练，气质拿捏得死死的，暧昧氛围也烘托得很到位。强强听起来就是舒爽。</li>\n<li>黑道老大暗恋卧底，还很不经撩，两次，没出息（bushi）</li>\n</ul>\n<p><strong>第二、三期</strong></p>\n<ul>\n<li>整体后期还是挺好的，第一期的动次打次跟古典舞曲，后面的打斗场面烘托气氛，就是有时候声音太大了炸耳朵。</li>\n<li>乔已和妹妹都挺惨的，被自己的信仰背叛，确实很折磨，但即使这样还能为此背叛严肆，着实是舍己为人了。林纾也是身不由己，爱没有对错，她却爱上了深恶痛绝的人（不过收网时是不是不能直接把嫌疑人干掉，这儿是 bug 吗？）。现实真残忍。</li>\n<li>好在是 HE，“不要留光头了，哥喜欢长发美人。” 够霸气哈哈，感觉这个老大有点恋爱脑</li>\n</ul>\n</div></details>\n<details class=\"success\"><summary>《满分赝品》皮皮鲨 X 陈想先生（主角：章献怀X林冬迟）</summary><div>\n<p><strong>第一期</strong></p>\n<ul>\n<li>Sandstorm 制作，连陈想的剧尺度都大起来了 [/ 允悲]，虽然只有事前事后，看见进度条上的唯一一张图片确认了没有完整版。</li>\n<li>披着狗血皮的纯爱故事，从车祸、失忆、替身开始，第一期就掉马了。节奏挺紧凑的，戏剧性也够，末了那句 “我的赝品，我得重新署上自己的名字” 也挺带感。</li>\n<li>林有点呆呆的但不笨，呆白甜，喜欢一个人的时候他赖床也可爱！跟人斗嘴也可爱！饿了偷吃玉米、被欺负了逃跑、时不时心虚、傲娇、被简单的示好感动，都挺可爱的～</li>\n</ul>\n</div></details>\n<details class=\"success\"><summary>《走狗》by商桐（役陆业征）X逆鳞无伤（役程展心）</summary><div>\n<p><strong>第四期</strong></p>\n<ul>\n<li>攻的声音不太男高</li>\n<li>误会还挺多，受为了不让攻受到牵扯所以也没太多解释，显得软弱 ​​​</li>\n</ul>\n<p><strong>第五期</strong></p>\n<ul>\n<li>受爸也太渣了，对他儿子都这么狠。</li>\n<li>攻也忒有钱了，随随便便 30w 就拿来还赌债。这时候程展心就能皮了，还能管着他爸了。这俩高中生有些社会了，对钱也没概念似的。</li>\n<li>YouTube 上的视频做得还挺用心的，还有片头、字幕。拉了兔兔来片尾报幕</li>\n</ul>\n<p><strong>第六期</strong></p>\n<ul>\n<li>在一起之后，尺度突然大起来了。</li>\n<li>陆业征认真地叫他心心的时候，感觉很温暖，程展心终于被正常地爱着了。</li>\n<li>解气，程展心把他爹的骨灰扬水沟里了（这段的哭戏很真实</li>\n</ul>\n</div></details>\n<details class=\"success\"><summary>《艳鬼》by昱霖（役空华）&糖醋排骨（役桑陌）</summary><div>\n<p><strong>第一期</strong></p>\n<ul>\n<li>早期糖糖的高贵小美人音诶～</li>\n<li>剧情听得云里雾里的，看着弹幕 get 了一点点，还是很懵，大概是 “我爱你你却爱他，我为你付出了一切你却转手送给他” 的剧情</li>\n</ul>\n<p><strong>第二期</strong></p>\n<ul>\n<li>一辆小车过去了。</li>\n<li>没有之前的记忆的空华，感觉是在抢回桑陌对则昀的爱，让他只看着自己。</li>\n<li>感觉角色太多了，很多都只出现了一下，也没有后文了（虽然可以衬托桑陌的好，以及空华对桑陌的弥补</li>\n</ul>\n<p><strong>第三期</strong></p>\n<ul>\n<li>三百年前桑陌为则昀欠下的债，都在还着，最终由空华解了。不过桑陌还是不相信他了，单方面觉得他心里只有南风</li>\n</ul>\n</div></details>\n<details class=\"success\"><summary>《折枝/阶下囚》燃X陈小C （段凌X陆修文）</summary><div>\n<p><strong>预告</strong></p>\n<ul>\n<li>简直就是虐点集锦吧。</li>\n</ul>\n<p><strong>上期</strong></p>\n<ul>\n<li>小 C 役的陆修文，（一如既往）是个嘴硬心软对重要的人特别有保护欲的傲娇，对弟弟和攻都特别好，还要不让对方太愧疚。</li>\n<li>可以理解为 “替身竟是白月光” 吗 [/ 笑 cry]</li>\n</ul>\n<p><strong>下期</strong></p>\n<ul>\n<li>\n<p>恃宠而骄的可爱劲儿，让人忍不住要宠他。然而只是爱而不得、苦中作乐。<br />\n开个车被叫弟弟的名字；眼瞎了也要摸一摸复习，好在奈何桥不要忘记。末了说 “这一日怎么这样短”；让人心疼。</p>\n</li>\n<li>\n<p>很为弟弟和攻着想，让弟弟瞒着攻十年前的真相，让攻瞒着弟弟自己命不久矣免得让弟弟伤心，结果他一走，这两人都立马告诉了对方，真不让人省心。<br />\n燃的哭戏很让人动容，更何况是这么好的修文。</p>\n</li>\n<li>\n<p>说好的这篇文一半虐一般糖，结果刚好停在了虐完的地方（宝宝心里苦</p>\n</li>\n<li>\n<p>p.s 陆修文真的很喜欢笑，笑起来感觉世界都亮了</p>\n</li>\n</ul>\n</div></details>\n<details class=\"success\"><summary>《阶下臣》by风允之（役赵驰）&林予曦（役何安）</summary><div>\n<p><strong>第八期</strong></p>\n<ul>\n<li>这期基本能盲听。</li>\n<li>一心搞事业，第八期了，还在一心搞事业，感情线终于有一点眉目了。事业线的逻辑还是比较通顺的。</li>\n<li>天空还是演技在线，娇媚和正气平衡得刚刚好。</li>\n<li>王阿有点意难平啊，一直对何安这么好，何安却没会意</li>\n<li>弹幕把 “厂工” 叫 “厂花” 可还行</li>\n</ul>\n<p><strong>第九期</strong></p>\n<ul>\n<li>高兴到破音，熟悉的破音哈哈。</li>\n<li>采青一事，不论是不是注定，只要何安为了达到目的递了刀子，都有错。他对盈香如何，采青也是别人的意中人、别人的女儿姐妹啊。所以何安说自己 “虚伪至极” 也没错</li>\n</ul>\n<p><strong>第十期</strong></p>\n<ul>\n<li>4' 处，天空的报幕好媚啊。主 cp 的感情线已经够慢的了，副 cp 也这么慢。</li>\n<li>车开起来了。不过按这个节奏看上去是应该 be 啊，搞了这么久事业，好歹甜一会儿吧</li>\n</ul>\n<p><strong>第十一期</strong></p>\n<ul>\n<li>有一点听疲了，听古耽最不适应的就是尊卑，何安太卑微了。不过哭哭啼啼的怪可爱的。</li>\n<li>适时地开了一点车。</li>\n</ul>\n<p><strong>第十二期</strong></p>\n<ul>\n<li>协役群杂音效后期依然在线。</li>\n<li>上期末尾何安和时开的对话，还挺稳的，有些 A 了，不过时开一走就泄气了，挺不容易的。</li>\n<li>本期搞事业 + 回忆。感情线着实比较少耶</li>\n</ul>\n</div></details>\n",
            "tags": [
                "广播剧",
                "广播剧",
                "整理"
            ]
        },
        {
            "id": "https://sneexy.github.io/2022/09/24/life/%E6%9E%81%E7%AE%80/",
            "url": "https://sneexy.github.io/2022/09/24/life/%E6%9E%81%E7%AE%80/",
            "title": "极简",
            "date_published": "2022-09-24T10:50:58.000Z",
            "content_html": "<h1 id=\"极简\"><a class=\"anchor\" href=\"#极简\">#</a> 极简</h1>\n<h2 id=\"物质上\"><a class=\"anchor\" href=\"#物质上\">#</a> <strong>物质上</strong></h2>\n<p><strong>断，减少物品的购买</strong>：</p>\n<ul>\n<li>\n<p>记账。把握消费度量</p>\n</li>\n<li>\n<p>物品分类。方便寻找，不容易多买。我的大类是：衣鞋，日用品，药品，电子，文娱。TODO：记录所有物品</p>\n</li>\n<li>\n<p>消耗品最多只囤几个月的用量</p>\n</li>\n<li>\n<p>非消耗品谨慎挑选购买，犹豫的可以在购物车放放，不太喜欢的就退掉</p>\n</li>\n</ul>\n<p><strong>舍，丢弃已有的物品</strong>：</p>\n<ul>\n<li>\n<p>偶尔大扫除</p>\n</li>\n<li>\n<p>拍照和记录。有一些东西只是留个念想</p>\n</li>\n</ul>\n<p><strong>剩下的东西，判断的标准就是 “心动” 和 “实用”。</strong></p>\n<ul>\n<li>\n<p>心动的东西分为两类：</p>\n<ul>\n<li>好看的东西，不想扔，摆出来，看着心情也会变好一些。</li>\n<li>十分珍惜之物，压箱底了。</li>\n</ul>\n</li>\n<li>\n<p>其他就是实用的东西，尽量趁手，不知不觉就用了几年，或者搬家时，用不上或实在不想搬的就丢了送了。</p>\n</li>\n</ul>\n<p>现在就是，虽然断舍离了，但也不是空空如也，刚好维持着极简和不孤独感的平衡，住到哪都有家的感觉。</p>\n<h2 id=\"精神上\"><a class=\"anchor\" href=\"#精神上\">#</a> <strong>精神上</strong></h2>\n<p><strong>社交网络上</strong>：</p>\n<ul>\n<li>\n<p>瀑布流类型的软件慎入</p>\n</li>\n<li>\n<p>用主动搜索获取信息，代替被动接收信息</p>\n</li>\n</ul>\n<p><strong>效率 APP：</strong></p>\n<ul>\n<li>减少对软件的依赖，目前用自带的备忘录 + 提醒事项</li>\n</ul>\n<p><strong>生活中</strong>：</p>\n<ul>\n<li>\n<p>经济独立是精神独立的支柱</p>\n</li>\n<li>\n<p>在心里善用 “关你屁事” 和 “关我屁事”，保持界限感（双向</p>\n</li>\n<li>\n<p>使用 Todo 列表整理所有待办，脑袋里只装最近要做的事</p>\n</li>\n</ul>\n<p>很重要的是，知道自己为什么要极简，至少是为了自己更开心，生活更舒服，如果到了为了极简而极简的地步，反而成为自己的包袱了。</p>\n<p>把不需要的东西扔掉，给不重要的东西预设丢掉的时间，省下的空间和时间精力，就能花在喜欢的、至少不讨厌的东西上了。</p>\n<p>第一版：<span class=\"exturl\" data-url=\"aHR0cHM6Ly93d3cuZG91YmFuLmNvbS9ub3RlLzgyMTE4MjI0Mg==\">极简为热爱腾出空间 —— 极简心得（豆瓣）</span></p>\n",
            "tags": [
                "生活",
                "极简"
            ]
        },
        {
            "id": "https://sneexy.github.io/2022/09/24/reading/%E8%AF%BB%E4%B9%A6%E7%AC%94%E8%AE%B0%EF%BC%9A%E6%96%AD%E8%88%8D%E7%A6%BB-%E5%B1%B1%E4%B8%8B%E8%8B%B1%E5%AD%90/",
            "url": "https://sneexy.github.io/2022/09/24/reading/%E8%AF%BB%E4%B9%A6%E7%AC%94%E8%AE%B0%EF%BC%9A%E6%96%AD%E8%88%8D%E7%A6%BB-%E5%B1%B1%E4%B8%8B%E8%8B%B1%E5%AD%90/",
            "title": "读书笔记：断舍离-山下英子",
            "date_published": "2022-09-24T10:46:14.000Z",
            "content_html": "<h1 id=\"读书笔记断舍离-山下英子\"><a class=\"anchor\" href=\"#读书笔记断舍离-山下英子\">#</a> 读书笔记：断舍离 - 山下英子</h1>\n<p>书：<span class=\"exturl\" data-url=\"aHR0cHM6Ly9ib29rLmRvdWJhbi5jb20vc3ViamVjdC8yNDc0OTQ2NS8=\">断舍离 (豆瓣) (douban.com)</span></p>\n<p>阅读时间：2015 年 8 月</p>\n<h2 id=\"目录\"><a class=\"anchor\" href=\"#目录\">#</a> 目录</h2>\n<ul>\n<li>前言</li>\n<li>第一章 只要了解个中奥妙，就能激发干劲 —— 断舍离的<strong>机制</strong></li>\n<li>第二章 我们为什么没办法收拾 ——<strong> 无法丢弃</strong>的理由</li>\n<li>第三章 先从整理头脑开始 —— 断舍离的<strong>思考</strong>法则</li>\n<li>第四章 身体开始行动 —— 断舍离的<strong>实践</strong>方法</li>\n<li>第五章 前所未有的畅快和解放感 —— 看不见的世界在<strong>变化</strong></li>\n<li>后记</li>\n</ul>\n<p><mark>断 = 断绝不需要的东西，舍 = 舍弃多余的废物，离 = 脱离对物品的执着。</mark></p>\n<p>通过学习和实践断舍离，人们将重新审视自己与物品的关系， 从关注物品转换为关注自我 —— 我需不需要，一旦开始思考，并致力于<mark>将身边所有 “不需要、不适合、不舒服” 的东西替换为 “需要、适合、舒服” 的东西</mark>，就能让环境变得清爽，也会由此改善心灵环境，从外在到内在，彻底焕然一新。</p>\n<h3 id=\"前言\"><a class=\"anchor\" href=\"#前言\">#</a> 前言</h3>\n<p>总而言之，断舍离就是通过收拾自己居住的空间，让自己从看得见的世界走向看不见的世界。因此，要采取的行动是 ——</p>\n<p><strong>断</strong>＝断绝想要进入自己家的不需要的东西。</p>\n<p><strong>舍</strong>＝舍弃家里到处泛滥的破烂儿。</p>\n<p>通过不断重复断和舍，最后会到达这样的状态：</p>\n<p><strong>离</strong>＝脱离对物品的执念，处于游刃有余的自在的空间。</p>\n<p>换句话说，<mark>断舍离的主角并不是物品，而是自己</mark>。</p>\n<p>你要做到的思考方式并不是 “这东西还能使，所以要留下来”， 而是 “我要用，所以它很必要”。 主语永远都是自己，而时间轴永远都是现在。现在自己不需要的东西就必须放手，只选择必要的物品。通过这个过程，你可以从看得见的世界走向看不见的世界，最终实现对自己的深刻、彻底的了解，并接纳最真实的自己。如此一来，不仅是居住环境，就连整个人的心灵都能轻松舒畅了</p>\n<h3 id=\"第一章-只要了解个中奥妙就能激发干劲断舍离的机制\"><a class=\"anchor\" href=\"#第一章-只要了解个中奥妙就能激发干劲断舍离的机制\">#</a> <strong>第一章 只要了解个中奥妙，就能激发干劲 —— 断舍离的机制</strong></h3>\n<ul>\n<li>\n<p><strong>从时间轴和关系轴看物品</strong></p>\n<ul>\n<li>时间轴，过去，当下，未来，何时能用</li>\n<li>关系轴，物品与自己的关系</li>\n</ul>\n</li>\n<li>\n<p><strong>筛选物品带来的自我察觉</strong></p>\n<p>要得到 “这种东西与当下的我很相称，对当下的我来说是必需品” 这样的判断，人就必须要清楚了解自己。通过不断地筛选物品的训练，当下的自我就会越来越鲜明地呈现在自己的眼前，人也就能以此判断出准确的自我形象</p>\n</li>\n<li>\n<p><strong>和物品成为好朋友</strong></p>\n<p>只有物品减少到了自己可以把握的量，也就是全都在自己的支配下了，才能把你自己变成物品的主人，才能达成先有自己，后有物品的状态。</p>\n</li>\n<li>\n<p><strong>磨砺内在的感应力</strong></p>\n<p>过多的物品令自己心烦不已，内在智慧就会变得迟钝，所以必须通过行动让它重回生机，而所谓行动，正是将家里 “不需要、不合适、不舒服” 的东西替换成 “需要、合适、舒服” 的东西。</p>\n</li>\n<li>\n<p><strong>东西要用才有价值</strong></p>\n<p>如果能通过断舍离，让一些我们并不需要的物品流向那些需要它们的地方，那就太完美了。</p>\n</li>\n</ul>\n<h3 id=\"第二章-我们为什么没办法收拾无法丢弃的理由\"><a class=\"anchor\" href=\"#第二章-我们为什么没办法收拾无法丢弃的理由\">#</a> <strong>第二章 我们为什么没办法收拾 —— 无法丢弃的理由</strong></h3>\n<ul>\n<li>\n<p><strong>捡便宜心理和折扣的陷阱</strong></p>\n<ul>\n<li>不要看便宜了多少，而要看自己是否需要，以及为购买花费了多少</li>\n</ul>\n</li>\n<li>\n<p><strong>入口是 “断” 的闸门，出口是 “舍” 的闸门</strong></p>\n<p>我们水池的入口闸门本来是打算关得死死的，可来自外部的物质的压力却不是一般的大，再加上贪便宜和商家布下的折扣陷阱，所以这闸门常常是打开的。可通往下游、负责排泄不需要的东西的出口的闸门，如果不是有意识努力的话，反倒不会开启，因为那上面已经长满了 “好可惜啊”、“垃圾分类太麻烦了” 这样的铁锈了。</p>\n</li>\n<li>\n<p><strong>香鱼变成鲶鱼了吗</strong></p>\n<p>我们就像鲶鱼一样，活在这个全是淤泥的环境里动弹不得。要是环境适宜的话，我们原本是能像居住于清水当中的香鱼一般来去自如的，可现如今却因为四处堆满了淤泥而无力游动</p>\n<p>如果非要问为什么人在这种环境下就会静静地不动弹，恐怕还有一个理由，就是如果乱翻腾的话，好不容易清澈了的上层水面也会变得浑浊不堪。静止不动的话，水就不会浑浊，这样的话还能有点喘息的空间。不过，要是下定决心实施断舍离，就必须得把池塘翻个天翻地覆</p>\n</li>\n<li>\n<p><strong>对现在的界定因人而异</strong></p>\n<p>说到底，觉得多长一段时间属于 “现在” 都可以，这是每个人的自由；但是一定要有对自己而言最合适的 “现在” 存在</p>\n</li>\n<li>\n<p><strong>扔不掉就是不想扔</strong></p>\n<p>虽说一样东西，你把它扔在一边置之不理还是精心保管，这中间是有一点差别的，但要是到了遗忘的地步，那它无论是以何种形式被收留着都没什么区别。从实质上来讲，它们已经是垃圾了</p>\n</li>\n<li>\n<p><strong>没有收拾的屋子就像便秘</strong></p>\n<p>在便秘的时候，病菌会不断释放毒素，这些毒素会被肠道再次吸收，而后扩散到身体各个部位，引起不适。当我们身处一个堆满垃圾和破烂儿的房间时，也等于是 24 小时不间断地吸收这些废物发出的废气。换句话说，房间里满是破烂儿，就会释放出影响心情的废气，让你不知不觉间陷入慢性中毒的状态</p>\n</li>\n<li>\n<p><strong>案例五 过期的千纸鹤</strong></p>\n<p>人很容易因为习惯了某件事而感觉麻痹，这实在是很可怕。无论一开始有多美好的回忆，可随着时间的流逝，一切也会发生变化，就好比是再美味的食物，搁久了也会变味一样。</p>\n<p>除掉废物、垃圾、灰尘，就能彻底除掉停滞运与腐败运。</p>\n</li>\n<li>\n<p><strong>当杂物占据了空间</strong></p>\n<p>说到底，堆积着的破烂儿就代表着 “良心不安的聚集”、“担忧的聚集”。我已经说过，在断舍离里，要把时间轴放在当下，而良心不安与担忧，其实是把时间轴错位到了过去与未来。</p>\n<p>我们先来看看良心不安吧。我们自身也会因为不能物尽其用而导致良心上的不安。</p>\n</li>\n</ul>\n<h3 id=\"第三章-先从整理头脑开始-断舍离的思考法则\"><a class=\"anchor\" href=\"#第三章-先从整理头脑开始-断舍离的思考法则\">#</a> <strong>第三章 先从整理头脑开始 —— 断舍离的思考法则</strong></h3>\n<ul>\n<li>\n<p><strong>时间轴要锁定在现在</strong></p>\n<p>我的感觉是，家里放着的东西，有八成都是时间轴错位到了过去或未来上的。</p>\n</li>\n<li>\n<p><strong>找回对自己的信任</strong></p>\n<p>人之所以会产生 “说不定以后能用得上呢”、“必须得扔掉了，可又没有行动” 这样的想法，多半是源于对自己的不信任。<mark>用和朋友之间的约定来打比方的话，这就容易理解了。</mark></p>\n<p>比方说我和朋友约好了吃午饭，但我却告诉朋友:“对不起，我突然有点急事，今天约好的午饭，咱们改约到下礼拜好不好？” 朋友很爽快地说:“没事儿，下礼拜也可以。” 结果到了下礼拜的那一天，我又对她说:“对不起，我今天也有点不方便，能不能改到再下周啊？” 因为已经是第二次了，所以朋友多少会有点火，可还巍:“好吧。不过，你可真够。啊，英子。” 然后就到了再下周，如果此时我又说 “对不起，我今天又突然不方便” 的话，如果我约的是你，你会怎么想？只是一次的话还能原谅，可要是接二连三地出现这种情况，你恐怕就会觉得 “和这家伙约好了也不可信，与其被她拖来拖去的，还不如干脆不跟她约定什么更好呢” 了吧？我的信誉度就会因此而骤然下降。可大家有没有对自己做过这种事呢？想着 “要用”，<mark>想着 “要处理那些破烂儿”，想着 “要扔掉”，可结果却根本置之不理，这就是拖延了与自己的约定。这种事日日重复，对自己的信任感就会一点点消失殆尽。</mark></p>\n</li>\n<li>\n<p><strong>由忽视和否定而来的能量</strong></p>\n<p>在断舍离里，我们可以认为被忽视的物品也是这样。尽管物品不会开口骂 “你这混蛋”，但我常年做这样的工作下来，是确实能感到它们在不停地抱怨说 “我好恨啊”。或许有人觉得，我把人和物品同样看待，实在是荒唐的无稽之谈，可物品原本就是因为你要用才留在手边的，而且也应该是因为这种想法才被带到家里来的。所以，如今你没有用它，这就相气于背叛了当时的关系。</p>\n</li>\n<li>\n<p><strong>让家成为最棒的放松地</strong></p>\n<p>假如回到家里，看见到处都是乱糟糟的，那我们恐怕会无意识地叹口气说 “累死了”。可如果家里是一尘不染的，那就很有可能在推开门的一瞬间<mark>说句 “果然还是回到家最放松啊” 这类积极的话</mark>了。这些话以及我们无意识的举止、表情、行为，其实对我们都有很大的影响。如果经常唉声叹气，那一起住的人也会跟着郁闷不已。即便是一个人独居，你的态度也会影响到你自己。可见，语言与动作也属于自己能改变的环境之一。</p>\n<p>居住环境是凭借一己之力可以改变的环境。要打造出能够款待自己的空间。</p>\n</li>\n<li>\n<p><strong>以自我为轴心，把时间轴放在当</strong>下</p>\n<p>至于 “舍” 的秘诀，就是完全地以自己为中心，并且以当下为时间轴。没有必要按照 “衣服篇”、“厨房篇” 之类不同的类别选择不同的方法，进行同样的思考就行了。</p>\n</li>\n<li>\n<p><strong>“自我轴心” 的窍门 — 注意提问时的主语</strong></p>\n<p>还是拿眼镜和筷子的例子来说，物品原本是因为 “我用” 才有价值。可多数人都说 “眼镜可以用”、“筷子可以用”，拿物品当了主语。这是把主角的位子拱手让给了物品，把焦点聚在物品上的状态。</p>\n<p>带着这种观点再回来看看我们的房间，你就会发现，只要是能装东西的地方，就全都塞满了买蛋糕时送的保温袋、已经干透了的湿纸巾、免费赠送的圆珠笔、住旅馆时送的小毛巾之类的杂物。== 这些东西很难说是 “经过精挑细选才留下来的”。也就是说，收纳这些东西，只不过在做垃圾分类。== 如果大量累积类似这样的东西，就说明自己已经进入了对物品的品质和数量毫无知觉的状态。这些在居住环境里放了好几个月，甚至放了好几年的东西，只不过因为不是生鲜食品所以才没有烂掉。但是如果从机能上来说，它们早已经腐烂了。置身于这样的环境中，就几乎等于是住在一个垃圾暂放室。</p>\n<p><mark>主语到底在哪里？主语到底是我还是物品？请养成经常如此自问的习惯吧。如果能养成这样的习惯，就会有意识地注意到物品的品质与数量，就能做出需要或不需要 的判断。</mark></p>\n</li>\n<li>\n<p><strong>将与物品的关系比作人际关系，了解当下的含义</strong></p>\n<p>如果把你与人的关系再往前发展一步，就到了需要确认能不能把对方叫做朋友的阶段。这个阶段，就要引入时间轴的概念了。也许某个人与你的关系在过去很不错，也就是说，某样东西过去曾经是对你很重要的宝贝，会让你涌出对过去的怀念和留恋。但在今天，这个人与你的价值观发生了分歧，已经不如从前那般亲密了。这种时候，与其勉强自己 “立马把这个人抛掉”，倒不如先适应现状，学会接受这种变化。换句话说，就是选择对当下的我来说最必要的朋友。（sne. 老板）</p>\n<p>非得这样的话，可能很多人都难免有些于心不忍。不过，除了个别极为特殊的例子之外，人际关系本来就是随着时间不断变化的，就算是莫名其妙地渐行渐远了，也可以心平气和地接受。不过遗憾的是，物品不会像人一样主动从你身边溜走，因此所有的判断及判断之后的行动 — 是扔掉，还是送去二手店，还是送给谁 — 都要由自己主动去做。   == 反复几次之后，你就能渐渐发现对当下的自己来说，什么是不必要的了。== 曾经有学员把这种状态形容为 “虽然在扔东西，可是垃圾却不停地冒出来”。在这种状态下，连街上卖的东西看起来也全都是垃圾了，人的思维模式真的可以改变到这种程度。在断舍离里，这种状态就叫做 “对破烂儿的 IQ’的提升</p>\n</li>\n<li>\n<p><strong>案例八 以一副假牙为契机，接受丈夫去世的事实</strong></p>\n<p>…… 只要把重要的回忆放在心里就好了，东西则完全可以扔掉，好让自己重新恢复当下该有的状态</p>\n<p><mark>选择物品的窍门，不是能不能用，而是我要不要用</mark>……</p>\n</li>\n<li>\n<p><strong>理清扫除的整体概念</strong></p>\n<p>不过是把东西放回原处，或者是把家里的东西改变一下形态，移动一下，甚至仅仅是挪开而已。<mark>只有把不需要的东西丢出家门，这才算是断舍离里的收拾。</mark></p>\n</li>\n<li>\n<p><strong>关注不扔东西造成的损失</strong></p>\n<p>那些占了八成的东西虽然几乎没有出场的机会，但却会时不时让我们觉得不安</p>\n</li>\n<li>\n<p><strong>“相” 的世界与意识世界</strong></p>\n<p>在改变环境的同时，你还会收获一种难以言喻的美妙感觉 — 一直堵在潜意识里的东西也一并被清理掉了。</p>\n<p>比方说，你拧开了厨房的水龙头想要放水，或者是你想要冲马桶，可因为下水道堵住了，所以你恐怕很难安心放水吧？就算打开水龙头，也总会有种担心和不安的感觉。如果把下水道修好，清理干净，知道 “下水道变通畅了” 的话，_那么你就能放心地打开水龙头了。这也就是说，潜意识里同意接收新的信息了，如此一来，有用的信息才能流进大脑里。潜意识之所以不允许新的信息进入，是因为被堵住了。就是因为意识被堵住了，所以人才不想敞开自己的心。（sne. 这就是我啊）</p>\n</li>\n<li>\n<p><strong>“可惜” 的两种含义</strong></p>\n<p>说到这，我想莽 2006 年当选滋贺县知事的嘉田由纪子知事。她当时以 “可惜” 为口号，要求终止正在施工中的新干线新站的建设。当初在制定建设计划的时候，该车站的便利性、高额的建设费等方面就已经备受质疑，而这些质疑的声音，也对嘉田知事的当选起到了推波助澜的作用。而另一方面，建设推进派则主张，施工现在已经开始了，“如果就此停工的话，实在太过 “可惜”。也就是说，在同一件事上，形成了<mark>两种 “可惜” 的对立</mark>。推进派认为 “已经建了一半了，所以要停止太可惜”，而知事方则认为 “继续在可用性极低的车站建设上支出经费，这实在太可惜了”。到底该不该建设这么一座新车站呢？</p>\n<p>…… 既然觉得可惜，就不该仅仅是把它拿回来收着，而是要去分享。正是因为觉得可惜，才不能为了未来的某一天可能会用到而将其无限期地保管起来，而是要把它送到此时此刻最为需要的地方去。</p>\n</li>\n<li>\n<p><strong>给还是觉得 “扔不掉”、“没法送人” 的你</strong></p>\n<p>像这样非把不需要的东西留在身边不可，真的会是物品的希望吗？因为物品没有生命，所以你或许不会以为物品也有自己的意志，那我就稍微变换一下提问的角度。把无法发挥原本作用的物品放在一边置之不理，或是随意对待自己镇本不喜欢的东西，再或者，明明根本不在意那个东西，却因为某些感情而留着它，你喜欢这样的自已吗？想必大多数人都不会喜欢这样的自己吧？因为要是把自己换到物品的位置上，被人这么对待的话，你一定会讨厌那个如此对待你的人。所以，只不过刚好是物品没有它们自己的意志和感情，而你则有罢了。</p>\n</li>\n</ul>\n<h3 id=\"第四章-身体开始行动断舍离的实践方法\"><a class=\"anchor\" href=\"#第四章-身体开始行动断舍离的实践方法\">#</a> <strong>第四章 身体开始行动 —— 断舍离的实践方法</strong></h3>\n<ul>\n<li>\n<p><strong>只集中于一点，把它搞完美。以此提高动机</strong></p>\n<p>从能用多少时间出发，找出今天想要进行断舍离的场所，这样的话效率更高，而且人也更愿意付出努力。换句话说，要选择的这个场所，即便只是一个抽屉也是可以的，甚至说得更夸张一点，即使只是一个塞满了购物小票的钱包也无所谓</p>\n</li>\n<li>\n<p><strong>根据目的选择不同的场所</strong></p>\n<p>希望能作用于心理深层</p>\n<p>着手于看不见的场所、不想看见的场所、不想让别人看见的场所等等，即便打扫干净了也不会有任何人发现，但是自己知道并且总是在意的场所，比如仓库、不怎么打开的收纳箱以及其他自己很在意的场所。</p>\n</li>\n<li>\n<p><strong>从 “怎么看都是垃圾” 的东西开始下手</strong></p>\n<p>大多数人都会在事后发觉:“会让我犹豫的东西，果然还是不需要。” 犹豫其实是感性接受考验的证据。</p>\n</li>\n<li>\n<p><strong>把东西送给别人时，要说 “请收下”</strong></p>\n<p>把自己用不着的东西送给有需要的人时，要说 “请收下”，不能说 “给你”。</p>\n</li>\n<li>\n<p><strong>从空间里限制物品数量</strong></p>\n<p>所谓收纳术，基本上来说就是加法解决法，是把不断增加增加再增加的东西都打包收起来，随着物品越耀多，收纳空间硫跟着越来越多，需要不停地增设新的收纳空间，然后物品继续增多，如此连锁循环。但以断舍离的观点看，花时间收纳不需要的东西，是不可能从根本上解决问题的。</p>\n</li>\n</ul>\n<h3 id=\"第五章-前所未有的畅快和解放感看不见的世界在变化\"><a class=\"anchor\" href=\"#第五章-前所未有的畅快和解放感看不见的世界在变化\">#</a> <strong>第五章 前所未有的畅快和解放感 —— 看不见的世界在变化</strong></h3>\n<ul>\n<li>\n<p><strong>试着使用高于自我形象的物品</strong></p>\n<p>我想，每个人都曾有过 “收拾了物品之后，不知道为什么，心情也变轻松了” 的感觉。不过，断舍离的目标是更高的大师级别。使用精挑细选的自己喜爱的东西，这样就能够挖掘出全新的自己，也就是说，物品并不只是用来使用的，而是要进入更高的阶段，最大限度地利用物品的力量。</p>\n<p>我在第一章里曾经写过，要刻意去使用一直因为可惜而没在用的回礼收到的麦森的杯子。“我没达到那种层次呢。”—— 一旦发现这种自我贬低的情况，就要有意识地允许自己使用更高级的东西，这就是运用加分法的过程。我之所以要以日常生活中经常都要用到的水杯为例子，也是有原因的，因为每天都在用的东西非常容易作用于潜意识。</p>\n<p>为了成为自色想成为的自己，先从日常使用的容器开始，进行意识上的革命吧。</p>\n</li>\n<li>\n<p><strong>关于 “碍事” 这个词</strong></p>\n<p>其实，根本没必要消除这种异样感，如果能够意识到让自己感到异样的原因，因此而卸下包袱，或是对此有所领悟，那么就不会徒增多余的压力了</p>\n</li>\n<li>\n<p><strong>从 “拥有” 这种观念中解放出来</strong></p>\n<p>我认为，所有物品归根到底都是我们从神祇、从地球手里借来的。</p>\n<p>一切有形的东西都是虚幻的，我们的心也是不断变化的。尽情地享受与物品难能可贵的短暂相遇，这一定就是我们所追求的幸福本身。当缘尽了，就潇洒地放手。不伍以寸物品，对一切的一切都能做到这样，这就是断舍离的愿望。</p>\n</li>\n</ul>\n<h3 id=\"后记\"><a class=\"anchor\" href=\"#后记\">#</a> <strong>后记</strong></h3>\n<ul>\n<li>\n<p><mark>物品要用才有价值一一是为断。</mark></p>\n<p>要意识到物品的数量和质量，要斩断用不完的物品、多余物品的流通。</p>\n</li>\n<li>\n<p><mark>物品在此时、当下，应出现在需要它的地方一一是为舍。</mark></p>\n<p>即便是以前用过的东西，如果现在已经不需要了，就不该怀着 “说不定将来还有一天能用得上” 的心情，随随便便地保存、管、收纳它，而是让它们去到此时此刻最需要它们的地方，要有意识地不断把物品送出去，“舍弃” 掉。</p>\n</li>\n<li>\n<p>物品处于恰当的位置，才能展现美感一一是为离。</p>\n<p>不断地重复拷问物品，也拷问自己的’‘断” 与 “舍”，挑选出与当下的自己最相称的物品。经过精挑细选筛选出的少量物品，<mark>能够各得其所，物品仿佛是回归了属于自己的空间一般的离开</mark>。</p>\n<p>通过整理肉眼看得见的环境，同时也整理自己，这就是人生该有的状态。</p>\n</li>\n</ul>\n",
            "tags": [
                "阅读",
                "断舍离",
                "极简",
                "读书笔记"
            ]
        },
        {
            "id": "https://sneexy.github.io/2022/09/07/drama/%E3%80%90%E6%B8%85%E6%B3%89-Sneexy%E3%80%912022%E5%B9%BF%E6%92%AD%E5%89%A7%E8%BF%BD%E6%9B%B4%E5%88%97%E8%A1%A8/",
            "url": "https://sneexy.github.io/2022/09/07/drama/%E3%80%90%E6%B8%85%E6%B3%89-Sneexy%E3%80%912022%E5%B9%BF%E6%92%AD%E5%89%A7%E8%BF%BD%E6%9B%B4%E5%88%97%E8%A1%A8/",
            "title": "【清泉-Sneexy】2022广播剧追剧列表",
            "date_published": "2022-09-07T15:37:09.000Z",
            "content_html": "<h1 id=\"清泉sneexy2022广播剧追剧列表\"><a class=\"anchor\" href=\"#清泉sneexy2022广播剧追剧列表\">#</a> 【清泉 / Sneexy】2022 广播剧追剧列表</h1>\n<p>备注：括号内为已听的期数</p>\n<h2 id=\"追平\"><a class=\"anchor\" href=\"#追平\">#</a> 追平</h2>\n<ul>\n<li>《闭嘴，你这假粉》龙盘 X 风允之：★★★★☆（7）\n<ul>\n<li>主角：沈谓行 X 叶九月</li>\n<li>质量很高的搞笑剧，风允之又受又欠的样子。</li>\n<li>天空客串</li>\n</ul>\n</li>\n<li>《义父》狼毛 X 天空 X 糖醋排骨：★★★★☆（5）\n<ul>\n<li>【22.2.21】主角：金小丰 X 陆雪征 X 叶崇义</li>\n<li>民国背景，人物很立体，配音后期等也很好。小疯子叶崇义配得特别好</li>\n</ul>\n</li>\n<li>《你怎么舍得让我的爱流向海》十六夜 / 擎苍 / HolyNightX 林予曦：★★★★（16）\n<ul>\n<li>【22.2.27】主角：顾鹏飞 / 陈旭阳 X 苏锐</li>\n<li>狗血是狗血，但人物心理很真实，所以比 188 更气听众。</li>\n<li>苏锐的性格比较拽和暴躁，林予曦在这部里戏感挺好</li>\n</ul>\n</li>\n<li>《像渡渡鸟一样死去》天空 X 倒霉死勒（1）\n<ul>\n<li>【22.3.10】主角：陆博远 X 裴子安</li>\n<li>没有预告那么虐，别是个小甜饼吧 ==</li>\n</ul>\n</li>\n<li>《我是主角的恶毒继弟》Mr. 岑（1）\n<ul>\n<li>【22.4.2】</li>\n<li>Mr. 岑的受土萌土萌的；观望 ing</li>\n</ul>\n</li>\n<li>《谢谢老板》风允之 X 林予曦（听完第二期上）\n<ul>\n<li>【22.5】</li>\n<li>挺搞笑的</li>\n</ul>\n</li>\n<li>《匿名投靠》倒吊男 X 矜持 ING（2）\n<ul>\n<li>【22.4.20】主角：路时 X 徐寒珉</li>\n<li>故事偏沙雕向。两个人相处尬中有序</li>\n<li>只听过倒吊男的报幕，上一次听角色还是骚气的袁瑞，这次是内心沙雕咆哮帝，外人看起来可能是怪蜀黍</li>\n</ul>\n</li>\n<li>《<span class=\"exturl\" data-url=\"aHR0cHM6Ly93d3cubWlzc2V2YW4uY29tL21kcmFtYS80NjAzMA==\">非正常契约夫夫</span>》擎苍 X 心外無物（1）\n<ul>\n<li>【22.6.1】主角：楚旌 X 暮轩然</li>\n<li>预告不错。剧情发展有点快，铺垫比较少。心外無物的声音虽然好听，但和预想的角色不太一样，比较软。</li>\n</ul>\n</li>\n<li>《<span class=\"exturl\" data-url=\"aHR0cHM6Ly93d3cubWlzc2V2YW4uY29tL21kcmFtYS8yODYxNA==\">爸爸和爸爸</span>》白玉京 X 林予曦（1）\n<ul>\n<li>【22.6.23】主角：龙铁军 X 方原</li>\n<li>开幕雷击。两个主角 40 + 的恋爱戏，兔兔压低了声线还是很软糯。</li>\n</ul>\n</li>\n<li>《我和替身渣攻恋爱后白月光回来了》续续点灯 X 陈小 C（1）\n<ul>\n<li>【22.6.27】主角：江衍 X 程见渝</li>\n<li>双替身，白月光 CV 声声慢，这个配音配置就很吸引我。陈小 C 唯唯诺诺和霸气的样子都好听，喜欢听他的笑，好仙啊。</li>\n</ul>\n</li>\n<li>《替罪羊》轩辕靖日 X 陈小 C（3 上）\n<ul>\n<li>【22.7.5】主角：薛擎 X 岑深</li>\n<li>小 C 策划，又是一直虐，虐身虐心的剧。（攻方朋友惊叹收心梗虽迟但到）</li>\n<li>小 C 压低了嗓音收起了美人音，还有点弱受，意外地不排斥，在医院从抗拒到犹豫到接受的过程配得很到位。主要配角羊仔，HolyNight。</li>\n</ul>\n</li>\n<li>《他・他》倔强的小红，天空，郝凡（上期）\n<ul>\n<li>【22.7.16】主角：舒朗，谈宁 / 谈臻，乔良宇</li>\n<li>原创剧，天空役双重人格，一个是女装大佬，一个是社恐程序员，设定比较有意思</li>\n</ul>\n</li>\n<li>《无耻之徒》斑马 X 笑意（第一期）\n<ul>\n<li>主角：姜晓宁 X 韩嘉；</li>\n<li>《法外之徒》的副 cp，看了小说很喜欢韩嘉，受了苦也不埋怨而是求出路。只更新到预告，小说鸽了十几年了，但是挺好看</li>\n</ul>\n</li>\n<li>《落不下》赵成晨，倒霉死勒\n<ul>\n<li>主角：段锐，段琰</li>\n</ul>\n</li>\n<li><span class=\"exturl\" data-url=\"aHR0cHM6Ly93d3cubWlzc2V2YW4uY29tL21kcmFtYS81NDUxNQ==\">《宣扬中华文化》</span>预告</li>\n<li><span class=\"exturl\" data-url=\"aHR0cHM6Ly93d3cubWlzc2V2YW4uY29tL21kcmFtYS81MDczNw==\">《满分赝品》</span>第一期\n<ul>\n<li>替身梗，陈小 C</li>\n</ul>\n</li>\n<li><span class=\"exturl\" data-url=\"aHR0cHM6Ly93d3cubWlzc2V2YW4uY29tL21kcmFtYS8zMjExMg==\">《08321》</span>第五期 + 番外 3\n<ul>\n<li>搞笑</li>\n</ul>\n</li>\n<li><span class=\"exturl\" data-url=\"aHR0cHM6Ly93d3cubWlzc2V2YW4uY29tL21kcmFtYS81NDgwMA==\">《溪亭日暮》</span>第一期上。\n<ul>\n<li>陈小 C，古风甜饼</li>\n</ul>\n</li>\n<li>《无罪释放》声展\n<ul>\n<li>陈小 C。</li>\n</ul>\n</li>\n</ul>\n<h2 id=\"追更\"><a class=\"anchor\" href=\"#追更\">#</a> 追更</h2>\n<ul>\n<li>【已完结】《庸俗喜剧》轩 ZoneX 糖醋排骨：★★★（6）</li>\n<li>《路人甲的爱情故事》朴枫（1）</li>\n<li>【已完结】《背负阳光》，第七期\n<ul>\n<li>【22.4.26】主角：林思东 / 容寂 X 解意</li>\n<li>矜持，完结，虐剧，要素集齐</li>\n<li>受有点万人迷，而且也太多糟心事了。</li>\n<li>连听了七期有点审美疲劳，跟看电视剧似的。</li>\n</ul>\n</li>\n<li>《彼此彼此》矜持 ING（1）</li>\n<li><span class=\"exturl\" data-url=\"aHR0cHM6Ly93d3cubWlzc2V2YW4uY29tL21kcmFtYS8yNDc2Mg==\">《谁把谁当真》</span>，听完上下</li>\n<li>【已完结】《飞行星球》天空，杨东旭（预告）</li>\n<li>【已完结】《泥中莲》商桐 X 倒霉死勒，上期</li>\n<li>《吞海》预告\n<ul>\n<li>主角：步重华 X 吴雩</li>\n</ul>\n</li>\n<li>《<span class=\"exturl\" data-url=\"aHR0cHM6Ly93d3cubWlzc2V2YW4uY29tL21kcmFtYS81MjQwMA==\">天官赐福</span>》预告\n<ul>\n<li>主题曲 PV 好好看</li>\n</ul>\n</li>\n<li>《<span class=\"exturl\" data-url=\"aHR0cHM6Ly93d3cubWlzc2V2YW4uY29tL21kcmFtYS8yNTYwOQ==\">大力出奇迹</span>》听完第一期\n<ul>\n<li>冬冬，攻音受，搞笑剧</li>\n</ul>\n</li>\n<li>《营销号说你喜欢我 第一季》DK X 冬冬，听完 5 期\n<ul>\n<li>冬冬的受音诶，这个声线我喜欢。有气质，不过内心 OS 是另一种风格，或委屈或搞笑或咆哮体，反差萌。冬冬的演技好好哦，很多情绪都拿捏得到位。</li>\n<li>剧的后期也不错。</li>\n</ul>\n</li>\n<li>《不能动》至尊宝 X 心外無物，预告</li>\n</ul>\n",
            "tags": [
                "广播剧",
                "广播剧",
                "整理"
            ]
        },
        {
            "id": "https://sneexy.github.io/2022/09/04/drama/CV/%E5%86%AC%E5%86%AC/",
            "url": "https://sneexy.github.io/2022/09/04/drama/CV/%E5%86%AC%E5%86%AC/",
            "title": "冬冬",
            "date_published": "2022-09-04T02:55:19.000Z",
            "content_html": "<p>对冬冬的何故念念不忘，很喜欢这个声线。收集一下略微有一些类似的：</p>\n<ul>\n<li>《撒野》，周敬。比何故年轻天真一点。</li>\n<li>《08321》，陈逸。比何故高冷一点。<span class=\"exturl\" data-url=\"aHR0cHM6Ly93d3cubWlzc2V2YW4uY29tL3NvdW5kL3BsYXllcj9pZD0yNjY3ODA2\">陈逸 - 声展 (missevan.com)</span>。话挺少的，听完觉得还是声展比较惊艳。</li>\n</ul>\n",
            "tags": [
                "广播剧",
                "声优",
                "声优"
            ]
        },
        {
            "id": "https://sneexy.github.io/2022/09/04/drama/2022-%E5%89%A7%E6%83%85%E6%AD%8C/",
            "url": "https://sneexy.github.io/2022/09/04/drama/2022-%E5%89%A7%E6%83%85%E6%AD%8C/",
            "title": "【清泉-Sneexy】2022已听剧情歌",
            "date_published": "2022-09-04T02:37:16.000Z",
            "content_html": "<h1 id=\"清泉-sneexy2022已听剧情歌\"><a class=\"anchor\" href=\"#清泉-sneexy2022已听剧情歌\">#</a> 【清泉 - Sneexy】2022 已听剧情歌</h1>\n<p>TODO: 平时没注意整理，这个没写完</p>\n<details class=\"success\"><summary>《设计师》天空，乘风归去：★★★（1）</summary><div>\n<ul>\n<li>【22.2.1】</li>\n<li>没有 get 到，可能需要看过小说才懂</li>\n</ul>\n</div></details>\n<details class=\"success\"><summary>《谁把谁当真》剧情歌-《扑朔迷黎》卡修 X 天空：★★★☆</summary><div>\n<ul>\n<li><span class=\"exturl\" data-url=\"aHR0cHM6Ly9tdXNpYy4xNjMuY29tLyMvc29uZz9pZD0xNDExOTI2MzMy\">《扑朔迷黎》- 网易云</span></li>\n<li>天空真是躺平了 ==，不过强受还是挺好的，温柔的黎朔（算上之前的番外，已经是第二次配黎朔了）</li>\n</ul>\n</div></details>\n<details class=\"info\"><summary>《观松月》倔强的小红 X 天空：★★★★（1）</summary><div>\n<ul>\n<li>【22.8.22】主角：乔天涯 X 姚温玉。出处《将进酒》</li>\n<li>一直都挺喜欢松玉这对的，一直是意难平，天空把姚温玉的脆弱和不甘配出来了，哭戏、弥留之际的虚弱、对松月的又希望他忘记又不希望他忘记的矛盾，都表现得刚刚好。</li>\n<li>剧情歌整体制作水平都挺高的。</li>\n</ul>\n</div></details>\n",
            "tags": [
                "广播剧",
                "广播剧",
                "整理"
            ]
        },
        {
            "id": "https://sneexy.github.io/2022/09/03/health/%E5%81%A5%E5%BA%B7%E5%85%BB%E7%94%9F/",
            "url": "https://sneexy.github.io/2022/09/03/health/%E5%81%A5%E5%BA%B7%E5%85%BB%E7%94%9F/",
            "title": "健康养生",
            "date_published": "2022-09-03T13:46:56.000Z",
            "content_html": "<h1 id=\"健康\"><a class=\"anchor\" href=\"#健康\">#</a> 健康</h1>\n<ul>\n<li>MEDS：Meditation 冥想，Exercise 锻炼，Diet 饮食，Sleep 睡眠</li>\n</ul>\n<h2 id=\"睡眠\"><a class=\"anchor\" href=\"#睡眠\">#</a> 睡眠</h2>\n<ul>\n<li>褪黑素（偶尔吃半份量</li>\n</ul>\n<h2 id=\"饮食\"><a class=\"anchor\" href=\"#饮食\">#</a> 饮食</h2>\n<ul>\n<li>到点就吃</li>\n<li>少吃辛辣，少吃甜食（如奶茶）、少喝饮料</li>\n<li>自己做饭替代外卖，少油少盐</li>\n</ul>\n<h2 id=\"锻炼\"><a class=\"anchor\" href=\"#锻炼\">#</a> 锻炼</h2>\n<ul>\n<li>视频跟练\n<ul>\n<li><span class=\"exturl\" data-url=\"aHR0cHM6Ly93d3cuYmlsaWJpbGkuY29tL3ZpZGVvL0JWMVZ0NDExWTduMQ==\">【周六野】20 分钟低难度有氧运动</span></li>\n<li><span class=\"exturl\" data-url=\"aHR0cHM6Ly93d3cuYmlsaWJpbGkuY29tL3ZpZGVvL0JWMVl4NDExdjdaMQ==\">10 分钟超燃脂 HIIT 有氧运动</span></li>\n<li><span class=\"exturl\" data-url=\"aHR0cHM6Ly93d3cuYmlsaWJpbGkuY29tL3ZpZGVvL0JWMTJ4NDExRDdxMQ==\">周六野，肩背</span></li>\n</ul>\n</li>\n<li>动作\n<ul>\n<li>肚子：波比跳、平板支撑、卷腹</li>\n</ul>\n</li>\n</ul>\n<h2 id=\"冥想\"><a class=\"anchor\" href=\"#冥想\">#</a> 冥想</h2>\n",
            "tags": [
                "健康"
            ]
        },
        {
            "id": "https://sneexy.github.io/2022/09/03/drama/%E6%B7%BB%E5%8A%A0%E5%89%A7%E9%9B%86%E6%9D%A1%E7%9B%AE%E7%9A%84SOP%E5%92%8C%E6%B3%A8%E6%84%8F%E4%BA%8B%E9%A1%B9/",
            "url": "https://sneexy.github.io/2022/09/03/drama/%E6%B7%BB%E5%8A%A0%E5%89%A7%E9%9B%86%E6%9D%A1%E7%9B%AE%E7%9A%84SOP%E5%92%8C%E6%B3%A8%E6%84%8F%E4%BA%8B%E9%A1%B9/",
            "title": "添加剧集条目的SOP和注意事项",
            "date_published": "2022-09-03T10:24:42.000Z",
            "content_html": "<p>豆友<span class=\"exturl\" data-url=\"aHR0cHM6Ly93d3cuZG91YmFuLmNvbS9wZW9wbGUvMjE3NzE2ODcv\">七姐 Claudia</span>  探索出来一种新办法，用正版碟的条形码给剧添加条目（低调），通过率飙升，自己有碟最方便。添加成功的剧，快来标记： <span class=\"exturl\" data-url=\"aHR0cHM6Ly93d3cuZG91YmFuLmNvbS9ncm91cC90b3BpYy8yNjUzMjA5MjIvP19pPTA2ODcwNjZOVm9BcTh5\">新建成功的剧集列表（一直更新 </span></p>\n<p>以下是目前的经验。如果添加条目后直接通过了，但是没有海报，说明是容易通过的类型。</p>\n<p>一些可能导致不通过的因素：最近几天有同一个条目未通过；使用最近未通过的条目的信息。有的我是添加几次才过的，有时比较严，SOP（太长不看定制版）是根据最严格的情况拟的。</p>\n<h3 id=\"sop太长不看定制版\"><a class=\"anchor\" href=\"#sop太长不看定制版\">#</a> <strong>SOP（太长不看定制版）</strong></h3>\n<p>如果手头有正版专辑且上面的 12/13 位条形码在音乐类型搜索无结果，按下面的 SOP 直接添加就行，然后记录下当前 “信息已成功提交，等待审核” 页面的链接，以便查看通过状态。</p>\n<p>如果人品值不够，有专辑也没通过，或者没有实体专，则：</p>\n<ol>\n<li>在 <span class=\"exturl\" data-url=\"aHR0cHM6Ly9tdXNpYy5kb3ViYW4uY29tL25ld19zdWJqZWN0\">新添唱片 (douban.com)</span> 填写唱片名（如果不过，尽量不含 “第 X 季”）</li>\n<li>在 <span class=\"exturl\" data-url=\"aHR0cDovL3d3dy5tNTgubmV0Lw==\">m58.net</span> 找条形码，即点进专辑，“条码（UPC）” 对应的数字（尽量不选择近几年的专辑，以及国内的）</li>\n<li>在 <span class=\"exturl\" data-url=\"aHR0cHM6Ly93d3cuZGlzY29ncy5jb20v\">discogs.com</span> 搜索此条形码，有结果就行</li>\n<li>在第一步的链接里填写条形码，点击下一步，如果给出提示并不能点到下一步，重复第二步</li>\n<li>百度搜索 “ISRC 豆瓣上有 ISRC 的专辑名”，看到同样的 ISRC 数字，并为 “CN-A23-16-02806” 格式的有短横线的，就复制下来，以备下一步使用</li>\n<li>填写表演者（主役），流派（原声），介质（Digit），发行时间（官方第一集发布时间，或无限中抓第一期发布时间），出版者（看简介中是谁出品，或者工作组，都没有就写策划），碟片数（随便），ISRC（上一步找到的 ISRC），简介（随意，如果不过，尽量不提广播剧）</li>\n<li>上传封面，可以点跳过，条目通过再传。</li>\n<li>记录下当前 “信息已成功提交，等待审核” 页面的链接，以便查看通过状态</li>\n<li>如果通过了，可以在 <span class=\"exturl\" data-url=\"aHR0cHM6Ly93d3cuZG91YmFuLmNvbS9ncm91cC90b3BpYy8yNjUzMjA5MjIvP19pPTA2ODcwNjZOVm9BcTh5\">新建成功的剧集列表</span> 里留言通过了哪一部</li>\n</ol>\n<h3 id=\"sop\"><a class=\"anchor\" href=\"#sop\">#</a> SOP</h3>\n<ol>\n<li>找一个没有用于音乐条目的正版条形码和 ISRC 码（不需要对应）</li>\n<li>在 <span class=\"exturl\" data-url=\"aHR0cHM6Ly9tdXNpYy5kb3ViYW4uY29tL25ld19zdWJqZWN0\">新添唱片 (douban.com)</span> 填写标题和条形码</li>\n<li>填写标题、出版者、出版时间，ISRC。（可选）添加其他更详细的信息（谨慎起见，我差不多都填了）。</li>\n<li>（可选）添加封面，上传</li>\n<li>（可选）如果添加了条目可以在<span class=\"exturl\" data-url=\"aHR0cHM6Ly93d3cuZG91YmFuLmNvbS9ncm91cC90b3BpYy8yNjUzMjA5MjIvP19pPTA2ODcwNjZOVm9BcTh5\">新建成功的剧集列表</span> 里留个言，避免同时重复添加了～</li>\n</ol>\n<h3 id=\"sop中的注意事项\"><a class=\"anchor\" href=\"#sop中的注意事项\">#</a> SOP 中的注意事项</h3>\n<h4 id=\"添加条目的必要选项\"><a class=\"anchor\" href=\"#添加条目的必要选项\">#</a> 添加条目的必要选项</h4>\n<ul>\n<li>一般的音乐条目：标题、出版者、出版时间。</li>\n<li>目前成功率高的方法，需要添加条形码和 ISRC，不要提是广播剧。</li>\n</ul>\n<h4 id=\"可能导致不通过的因素\"><a class=\"anchor\" href=\"#可能导致不通过的因素\">#</a> 可能导致不通过的因素</h4>\n<ul>\n<li>一个条目未通过后需要隔几天再申请</li>\n<li>使用了近期未通过的申请信息</li>\n<li>一次提交太多？（可能是玄学）一次加 3 个比较稳</li>\n</ul>\n<h4 id=\"条形码\"><a class=\"anchor\" href=\"#条形码\">#</a> 条形码</h4>\n<ul>\n<li>条形码需要满足的条件：正版 cd/dvd 等的条形码；在音乐类别搜索无结果</li>\n<li>提示：尽量找有多版本的老专辑，避免影响到新专辑的标记</li>\n<li>条形码的格式：12 位 - 13 位。如果有实体 cd/dvd，就直接是条形码下方的数字。<span class=\"exturl\" data-url=\"aHR0cHM6Ly96aGlkYW8uYmFpZHUuY29tL3F1ZXN0aW9uLzI3MzA4OTkzNS5odG1s\">条形码各个数字代表什么？</span></li>\n<li>建议查找方式：</li>\n<li>方法一：参考了找<span class=\"exturl\" data-url=\"aHR0cHM6Ly93d3cuZG91YmFuLmNvbS9ncm91cC90b3BpYy8xMDk4OTk0Lz9faT0wNzgzNjUwTlZvQXE4eQ==\">音乐条码的技巧 </span>，步骤：</li>\n<li>选择在 <span class=\"exturl\" data-url=\"aHR0cDovL3d3dy5tNTgubmV0Lw==\">m58.net </span>（点进专辑，找到 “条码（UPC）” 对应的数字），或在 <span class=\"exturl\" data-url=\"aHR0cHM6Ly93d3cuZy1tdXNpYy5jb20udHcv\">g-music.com.tw</span> 找条形码（國際條碼）</li>\n<li>在<span class=\"exturl\" data-url=\"aHR0cHM6Ly93d3cuZGlzY29ncy5jb20v\"> discogs.com</span> 搜索此条形码，有结果就行，确保它是正版</li>\n<li>方法二：直接在<span class=\"exturl\" data-url=\"aHR0cHM6Ly93d3cuZGlzY29ncy5jb20v\"> discogs.com</span> 搜索条形码（这种方法需要添 isrc）</li>\n<li>有些网站上叫做 ISBN（下策）</li>\n<li>豆瓣建议的搜条形码的地方\n<ul>\n<li>&gt; <span class=\"exturl\" data-url=\"aHR0cDovL3d3dy5hbWF6b24uY24vc2VhcmNoL3NlYXJjaC5hc3A/c2VhcmNoVHlwZT0mYW1wO3NlYXJjaFdvcmQ9JUU1JTk0JUIxJUU3JTg5JTg3JUU1JTkwJThEJmFtcDtzZWFyY2hLaW5kPWtleXdvcmQmYW1wO2Jlc3RTYWxlTnVtPTMmYW1wO3BhZ2VsZXRpZD1oZWFkc2VhcmNo\">去亚马逊搜索 唱片名</span></li>\n<li>&gt; <span class=\"exturl\" data-url=\"aHR0cHM6Ly93d3cuZGlzY29ncy5jb20vc2VhcmNoLz9xPSVFNSU5NCVCMSVFNyU4OSU4NyVFNSU5MCU4RCZhbXA7dHlwZT1hbGw=\">去 Discogs 搜索 (英语) 唱片名</span>（Barcode）</li>\n<li>&gt; <span class=\"exturl\" data-url=\"aHR0cHM6Ly9iYW5kY2FtcC5jb20vc2VhcmNoP3E9JUU1JTk0JUIxJUU3JTg5JTg3JUU1JTkwJThE\">去 Bandcamp 搜索 (英语) 唱片名</span></li>\n<li>&gt; <span class=\"exturl\" data-url=\"aHR0cDovL3d3dy5lc2xpdGUuY29tL1NlYXJjaF9Qcm8uYXNweD9xdWVyeT0lRTUlOTQlQjElRTclODklODclRTUlOTAlOEQmYW1wO3BhZ2Vjb3VudD0xMCZhbXA7Y2F0PTA=\">去誠品網路書店搜索 (繁体) 唱片名</span></li>\n<li>&gt; <span class=\"exturl\" data-url=\"aHR0cDovL2NkLmNpYW8uY28udWsvc2VhcmNoLnBocD9TZWFyY2hTdHJpbmc9JUU1JTk0JUIxJUU3JTg5JTg3JUU1JTkwJThEJmFtcDtUb3BDYXRlZ29yeT0w\">去 ciao.co.uk 搜索 (英语) 唱片名</span></li>\n<li>&gt; <span class=\"exturl\" data-url=\"aHR0cDovL3NjaC5qYm9vay5qcC9zLmFzcD9jYXRlZ29yeV9pZD0zMSZhbXA7ZmllbGQ9cCZhbXA7a2V5PSVFNSU5NCVCMSVFNyU4OSU4NyVFNSU5MCU4RCZhbXA7bWF4PTEwMA==\">去 JBOOK 搜索 (日语) 唱片名</span></li>\n<li>&gt; <span class=\"exturl\" data-url=\"aHR0cDovL3d3dy5nb29nbGUuY29tL3NlYXJjaD9xPSVFNSU5NCVCMSVFNyU4OSU4NyVFNSU5MCU4RA==\">去 Google 搜索 唱片名</span></li>\n<li>&gt; <span class=\"exturl\" data-url=\"aHR0cDovL3d3dy5iYWlkdS5jb20vcz93ZD0lRTUlOTQlQjElRTclODklODclRTUlOTAlOEQmYW1wO2NsPTM=\">去百度搜索 唱片名</span></li>\n</ul>\n</li>\n</ul>\n<h4 id=\"出版者\"><a class=\"anchor\" href=\"#出版者\">#</a> 出版者</h4>\n<ul>\n<li>在猫耳上的剧，看剧集介绍的里是谁 “出品”，出版者就是谁</li>\n<li>网剧可以写工作组</li>\n</ul>\n<h4 id=\"isrc\"><a class=\"anchor\" href=\"#isrc\">#</a> ISRC</h4>\n<ul>\n<li>可以和已有的条目的 isrc 重复，可以地区不同，可以在 isrc 查询网站查不到，只要是有效的就行。目前我通过 discogs 添加的都有这一项，注意数字间 “-” 的位置要跟原始的一模一样，不能删改。</li>\n</ul>\n<h4 id=\"判断条目审核状态\"><a class=\"anchor\" href=\"#判断条目审核状态\">#</a> 判断条目审核状态</h4>\n<p>一般的条目等通知过不过就行了。剧有时不通知审核状态，自己查询的办法：</p>\n<ul>\n<li>添加条目后，保存 “信息已成功提交，等待审核” 页面的链接</li>\n<li>如果页面 “不存在”，说明已经通过 / 不通过，搜标题可以判断是否通过</li>\n<li>如果页面还是提交时的状态，说明还待审核</li>\n</ul>\n",
            "tags": [
                "广播剧"
            ]
        },
        {
            "id": "https://sneexy.github.io/2022/09/01/life/%E7%90%86%E8%B4%A2/",
            "url": "https://sneexy.github.io/2022/09/01/life/%E7%90%86%E8%B4%A2/",
            "title": "理财",
            "date_published": "2022-09-01T00:17:33.000Z",
            "content_html": "<ul>\n<li>\n<p>理财第一条：<strong>不碰股票</strong></p>\n</li>\n<li>\n<p>基金：<strong>货币 A</strong>（低风险，包括余额宝），货币 B 中低风险，货币 C 中 / 高风险。</p>\n</li>\n<li>\n<p>银行理财</p>\n<ul>\n<li>招商银行\n<ul>\n<li><strong>朝朝宝</strong>（可以，不过利率也在降。最高 5w，活期）</li>\n<li><s>月月宝、季季宝、半年宝</s>（坑）</li>\n</ul>\n</li>\n</ul>\n</li>\n<li>\n<p>黄金</p>\n<ul>\n<li>金条：需要注意买可回购的黄金，比如 “中国黄金” 官方店，但是售价偏高。</li>\n<li><s>支付宝的：手续费</s></li>\n<li>纸黄金：可以，但是很多银行不卖了</li>\n</ul>\n</li>\n<li>\n<p>定期</p>\n<ul>\n<li>12 存单法、24 存单法、36 存单法</li>\n<li><span class=\"exturl\" data-url=\"aHR0cHM6Ly93d3cuY2FkZm9yZXguY29tL3RfeWhsbC9kaW5ncWkuaHRtbA==\">银行定期利率表 2022 最新利率，定期利率表一览（最完整版） - 财梯网 (cadforex.com)</span> （只作参考）</li>\n</ul>\n</li>\n<li>\n<p>reits：不懂，先不碰</p>\n</li>\n</ul>\n<p><strong>总结</strong>：综合了一下，手头留一部分活钱，然后每个月攒下的钱：</p>\n<ul>\n<li>第一年：分为 3 等份，分别存 1、2、3 年定期</li>\n<li>第二年：到时候再想，反正最终都要变成 3 年期</li>\n</ul>\n",
            "tags": [
                "生活"
            ]
        },
        {
            "id": "https://sneexy.github.io/2022/08/28/drama/%E3%80%90Sneexy%E3%80%912021%E5%B9%BF%E6%92%AD%E5%89%A7%E5%90%AC%E5%89%A7%E8%AE%B0%E5%BD%95/",
            "url": "https://sneexy.github.io/2022/08/28/drama/%E3%80%90Sneexy%E3%80%912021%E5%B9%BF%E6%92%AD%E5%89%A7%E5%90%AC%E5%89%A7%E8%AE%B0%E5%BD%95/",
            "title": "【Sneexy】2021广播剧听剧记录",
            "date_published": "2022-08-28T10:29:25.000Z",
            "content_html": "<h1 id=\"sneexy2021广播剧听剧记录\"><a class=\"anchor\" href=\"#sneexy2021广播剧听剧记录\">#</a> 【Sneexy】2021 广播剧听剧记录</h1>\n<h2 id=\"年终小结\"><a class=\"anchor\" href=\"#年终小结\">#</a> 年终小结：</h2>\n<ul>\n<li>听中文广播剧的元年</li>\n<li>剧情第一，声音第二</li>\n<li>喜欢有真实感、细腻的剧</li>\n<li>一般是喜欢哪个声音就逮着薅，一路的墙头：\n<ul>\n<li>姜广涛。实力派，但是后续没有发现风格对口的经典剧的主役受</li>\n<li>羊仔。挺可爱的，聒噪</li>\n<li>小随。戏感很好，受而不弱</li>\n<li>何故声线的冬冬</li>\n<li>陈张太康。挺甜的</li>\n<li>倒霉死勒。喜欢听他比较 man 声线的受。戏感挺好。听 cut 还挺可爱，声音和脸不贴</li>\n<li>天空。女王受，很喜欢天空配的江停</li>\n</ul>\n</li>\n</ul>\n<h2 id=\"听剧列表\"><a class=\"anchor\" href=\"#听剧列表\">#</a> 听剧列表</h2>\n<p>补记的所以内容比较少，想起了再补补吧</p>\n<p>（🔖 豆瓣已标记）《作品名》；评分；主役；主角；简评（有条目的略）（n 刷 *）</p>\n<ol>\n<li>🔖《<strong>将进酒</strong> 第一季》；★★★★★；袁铭喆 X 姜广涛；萧驰野 X 沈兰舟；关注姜 sir 的开始</li>\n<li>《<strong>将进酒</strong> 第二季》；★★★★★；袁铭喆 X 姜广涛；萧驰野 X 沈兰舟；</li>\n<li>🔖《<strong>迪奥先生</strong> 第一季》；★★★★；景向谁依 X 羊仔；张臣扉 X 焦栖；从羊仔最正经的剧入坑，关注羊仔的开始</li>\n<li>《<strong>迪奥先生</strong> 第二季》；景向谁依 X 羊仔；张臣扉 X 焦栖；</li>\n</ol>\n<details class=\"info\"><summary>5. 🔖《小白杨》；★★★★；八千里路X羊仔；俞风城X白新羽；</summary><div>\n<ul>\n<li>广播剧好听，但是删减了很多细节，于是想象着羊仔的声音看了原作再回来听。广播剧给小说添彩了。</li>\n<li>ed 也好听而且贴剧情。</li>\n<li>因为几乎没给俞第一视角所以忽略了很多他内心的纠结，本来是个立体的角色，一堆人在弹幕从头到尾刷 “渣” 很无聊。</li>\n</ul>\n</div></details>\n<details class=\"success\"><summary>6. 《一拜天地》；★★★☆；北落师门 X 小随；水三X秦书；</summary><div>\n<ul>\n<li>cv 声音很自然，而且受也不刻意文弱，喜欢这个声音。（关注小随的开始）</li>\n<li>情节有点少，没听够。</li>\n</ul>\n</div></details>\n<details class=\"success\"><summary>7. 《裸替》；★★★；图特哈蒙X羊仔；</summary><div>\n<ul>\n<li>细讲应该有很多细节，但是每一个地方都给足了细节，反而导致情节太少，感情铺垫不充分。</li>\n<li>羊仔声音好听。</li>\n</ul>\n</div></details>\n<ol start=\"8\">\n<li>[不更]<strong>《你却爱着一个傻逼》</strong>；夙七烈 X 卡修</li>\n<li>🔖《<strong>一醉经年</strong>》；★★★★☆；轩 ZoneX 冬冬；宋居寒 X 何故；冬冬的声音太好听，喜欢何故，人间清醒，清醒着沉沦</li>\n<li>《<strong>救赎</strong>》；★★★☆；胡良伟 X 小随；林奕 X 王邛；故事很短，但是感情很真切，小随声音好听，对 “那一刻，我真的好想活下去” 印象深刻</li>\n<li>🔖《<strong>我嗑了对家 X 我的 CP</strong> 第一季》；★★★★；刘思岑 X 陈张太康；顾依凉 X 卫言梓；挺搞笑的，冬天听了心情会好。陈张太康的声音好甜啊。</li>\n<li>《<strong>我嗑了对家 X 我的 CP</strong> 第二季》；★★★★；刘思岑 X 陈张太康；顾依凉 X 卫言梓；</li>\n</ol>\n<details class=\"info\"><summary>13. 🔖《碎玉投珠 第一季》；★★★★☆；凌飞X陈张太康；丁汉白X纪慎语；</summary><div>\n<ul>\n<li>真是温润如玉的一部作品，广播剧把剧情一点点铺开，就像是给你一点点看玉件的细节。</li>\n<li>配音和后期都很好，画面感很足，歌也好听。</li>\n<li>听花絮里边江导戏，说太康声音不要太虚，不虚才是理想中的状态，有些攻受分得太清都违和，除了可爱挂的，不太喜欢弱受。珍珠这个角色挺很立体。</li>\n</ul>\n</div></details>\n<details class=\"info\"><summary>14. 《碎玉投珠 第二季》；★★★★☆；凌飞X陈张太康；丁汉白X纪慎语；</summary><div>\n<ul>\n<li>蜕变。</li>\n<li>整体还是比较顺利的，爱情事业两不误，很配。</li>\n<li>瞎眼张给老梁送行说等他自己百年之后没人配给他送行那段儿哭了。</li>\n</ul>\n</div></details>\n<details class=\"info\"><summary>15. 《活受罪》；★★★★；倔强的小红军X倒霉死勒；沈凉生X秦敬；</summary><div>\n<ul>\n<li>虐点太高了没被虐到。不过配得还不错，没感觉原作很超神，</li>\n<li>音量有点没控制好，其他都不错。<span class=\"spoiler\" title=\"你知道得太多了\">倒霉死勒喘得还不错～</span></li>\n</ul>\n</div></details>\n<details class=\"success\"><summary>16. 《王子病的春天 第一季》；★★★☆；倔强的小红军X倒霉死勒；谭睿康X赵遥远；</summary><div>\n<ul>\n<li>喜欢这部里面倒霉死勒的声线。</li>\n<li>故事本身听到这还觉得不怎么虐，谁没有过失败的暗恋呢，就算是异性也不一定就能心想事成。</li>\n<li>细节蛮足的。</li>\n</ul>\n</div></details>\n<details class=\"info\"><summary>17. 《王子病的春天 第二季》；★★★★☆；倔强的小红军X倒霉死勒；谭睿康X赵遥远；</summary><div>\n<ul>\n<li>日常太多，有点流水，不过中后期遥远哭的那几场挺好，角色还算丰满。</li>\n<li>梅梅声音好听，man，从前期到后期的变化也很到位</li>\n</ul>\n</div></details>\n<details class=\"success\"><summary>18. 🔖《网恋翻车指南》；★★★☆；袁铭喆X倒霉死勒；向淮之X景欢；</summary><div>\n<ul>\n<li>反差萌。梅梅男声好听。</li>\n<li>感觉后期有点拉，场景切换有些生硬，有时候是语音还给打字的效果音。</li>\n</ul>\n</div></details>\n<details class=\"info\"><summary>19. 《将进酒 第三季》；★★★★★；袁铭喆X姜广涛；萧驰野X沈兰舟；</summary><div>\n<ul>\n<li>原作、配音、后期、时长都挺好，制造了很多名场面。感觉姜 sir 有时候鼻音比较重。</li>\n<li>可惜了松玉。</li>\n</ul>\n</div></details>\n<ol start=\"20\">\n<li>《<strong>塑料姐妹花二三事</strong>》；★★★★；小随 X 倒霉死勒；；认真在搞笑，绝对是没听过的小随和倒霉死勒的风格</li>\n<li>《<strong>金刚姐妹花二三事</strong>》；★★★；；；上一个的姊妹篇</li>\n<li>🔖《<strong>彼得・潘与辛德瑞拉 第一季</strong>》；景向谁依 X 羊仔；谢竹星 X 王超；cut 是真逗，但正剧就有些无聊，搞笑是 cv 撑起来的</li>\n</ol>\n<details class=\"success\"><summary>23. 《强制fq》；★★★☆；今宵X倒霉死勒；</summary><div>\n<p>故事虽小但比较完整，故事流畅，<span class=\"spoiler\" title=\"你知道得太多了\">h 比较给力</span>，就是受音太攻</p>\n</div></details>\n<ol start=\"24\">\n<li>《<strong>彼得・潘与辛德瑞拉 第二季</strong>》；景向谁依 X 羊仔；谢竹星 X 王超；成长了</li>\n<li>《<strong>我的目标是不坐牢</strong>》；★★★☆；倒霉死勒 X 卡修；李璧 X 方沐；又爱撒娇又爱打直球的年下诱攻 VS OS 机受。还挺新奇的搭配</li>\n<li>《<strong>招煮饭阿姨，男女不限</strong>》；★★★；小丑 X 小随；张来福 X 钟有礼；方言攻，感觉也不是很搞笑。小随声音好听</li>\n<li>《<strong>话梅</strong>》；★★★☆；kinsenX 小 K；顾十一 X 顾丑；故事比较完整，小 K 的哭腔不错。这十一怎么一点信任都没有，好过分</li>\n</ol>\n<details class=\"success\"><summary>28. 🔖《撒野 第一季》；★★★☆；倒霉死勒，涅槃；顾飞，蒋丞；</summary><div>\n<p>①对非原著党不友好，不好把握情节走向和主角性格，故事承接不够自然；（看评论说在猫耳删减过几次）<br />\n②既然后期蒋丞声音要软下去，一开始就不用沉那么低，最开头两个人声音有点像；梅梅声音好听；终于听到冬冬类似何故的声线，好听；<br />\n③顾飞还挺温柔，会织帽子、包扎，难以想象玩着消消乐、微信昵称小兔子乖乖还能当老大，怎么得到 “钢厂小霸王” 称号的</p>\n</div></details>\n<details class=\"info\"><summary>29. 🔖《撒野 第二季》；★★★★☆；倒霉死勒，涅槃；顾飞，蒋丞；</summary><div>\n<ul>\n<li>渐入佳境，前面的铺垫用上了，感情线和故事线都展开了，人物性格也开始丰满了。</li>\n<li>编剧的删改有些挺一言难尽的</li>\n<li>导演和配音很优秀，倒霉死勒的声音本来就带着克制收敛，专注于自己的小世界，又乖又有耐心，有治愈的能力，很贴顾飞，顾飞本飞</li>\n</ul>\n</div></details>\n<details class=\"info\"><summary>30. 🔖《撒野 第三季》；★★★★☆；倒霉死勒，涅槃；顾飞，蒋丞；</summary><div>\n<ul>\n<li>生日，吃醋，演奏，高考。</li>\n<li>“后面有你，我就踏实；你睁开眼，我会听见。”</li>\n<li>蒋丞前进的时候，拉着顾飞也一起。</li>\n<li>剧情改得还是有点不连贯</li>\n</ul>\n</div></details>\n<details class=\"info\"><summary>31. 🔖《撒野 第四季》；★★★★★；倒霉死勒，涅槃；顾飞，蒋丞；</summary><div>\n<ul>\n<li>失而复得。</li>\n<li>情绪捏得很稳，蒋丞的快乐到消沉，顾飞的消沉崩溃到自责，然后到最后的温暖。多亏蒋丞一路坚持，终于等到了顾飞睁眼</li>\n</ul>\n</div></details>\n<details class=\"info\"><summary>32. 🔖《破云 第一季》*；★★★★；阿春X天空；严峫X江停；</summary><div>\n<ul>\n<li>天空声音好听。关注天空的开始；只在这部里 get 到景向谁依的戏感</li>\n<li>剧情还行，画个图才把关系理清了；</li>\n</ul>\n</div></details>\n<ol start=\"33\">\n<li>🔖《破云 第二季》；；阿春 X 天空；严峫 X 江停</li>\n<li>🔖《破云 第三季》；；阿春 X 天空；严峫 X 江停</li>\n</ol>\n<p>Sneexy 2022</p>\n",
            "tags": [
                "广播剧",
                "广播剧",
                "整理"
            ]
        },
        {
            "id": "https://sneexy.github.io/2022/08/27/drama/CV/%E7%A5%9E%E8%B0%B7%E6%B5%A9%E5%8F%B2/",
            "url": "https://sneexy.github.io/2022/08/27/drama/CV/%E7%A5%9E%E8%B0%B7%E6%B5%A9%E5%8F%B2/",
            "title": "神谷浩史",
            "date_published": "2022-08-27T15:53:09.000Z",
            "content_html": "<h1 id=\"神谷浩史\"><a class=\"anchor\" href=\"#神谷浩史\">#</a> 神谷浩史</h1>\n<p>已听：<span class=\"exturl\" data-url=\"aHR0cHM6Ly9tdXNpYy5kb3ViYW4uY29tL3Blb3BsZS9TbmVleHkvY29sbGVjdD9zdGFydD0xJmFtcDtzb3J0PXRpbWUmYW1wO3JhdGluZz1hbGwmYW1wO3RhZz0lRTclQTUlOUUlRTglQjAlQjclRTYlQjUlQTklRTUlOEYlQjI=\">豆瓣 - 听过 - 标签 - 神谷浩史</span></p>\n<p>第一部听的 Drama 就是慈英臣系列《しなやかな熱情》。经典广播剧系列有很多，慈英臣（三木真一郎 X 神谷浩史）、言叶花（小野大辅 X 神谷浩史）、同级生（神谷浩史 X 野岛健儿）、清涧寺（游佐浩二 X 神谷浩史）。</p>\n",
            "tags": [
                "广播剧",
                "声优",
                "声优"
            ]
        },
        {
            "id": "https://sneexy.github.io/2022/08/27/drama/CV/%E6%9E%97%E4%BA%88%E6%9B%A6/",
            "url": "https://sneexy.github.io/2022/08/27/drama/CV/%E6%9E%97%E4%BA%88%E6%9B%A6/",
            "title": "林予曦",
            "date_published": "2022-08-27T15:52:13.000Z",
            "content_html": "<h1 id=\"林予曦\"><a class=\"anchor\" href=\"#林予曦\">#</a> 林予曦</h1>\n<p>听他的经典之作《法外之徒》入坑。<br />\n软糯又带点气质，很适合配有个性的角色，倨傲或乖顺忍耐的都好。<br />\n选剧本不太行。<br />\n唱歌好听。<br />\n没有偶像包袱，剧里该破音就破音 hhh<br />\n 不论剧本咋样，人设突不突出，有的剧喜欢得不得了，有的听不动，玄学。</p>\n<h2 id=\"歌曲\"><a class=\"anchor\" href=\"#歌曲\">#</a> 歌曲</h2>\n<ul>\n<li>《林予曦（兔兔）歌曲不完全合集》里：\n<ul>\n<li><span class=\"exturl\" data-url=\"aHR0cHM6Ly93d3cubWlzc2V2YW4uY29tL3NvdW5kL3BsYXllcj9pZD0yOTY3MDc1\">好汉歌 (missevan.com)</span> ：精准破音 hhh</li>\n</ul>\n</li>\n</ul>\n<h2 id=\"歌会repo\"><a class=\"anchor\" href=\"#歌会repo\">#</a> 歌会 Repo</h2>\n<details class=\"success\"><summary>22.9.17的歌会repo</summary><div>\n<p>录了音嗓子哑，适合唱苦情歌囧 rz</p>\n<p>《小嫦娥》<br />\n可爱，还以为是鹅歌</p>\n<p>40’左右，放了疯狂星期四的歌😂还以为跳过了这个话题呢，一本正经的，听到歌词才发现</p>\n<p>49' 翻唱梁静茹的《情歌》</p>\n<p>打了至少第三个嗝了！<br />\n两个厕所（什么奇怪的计数君）</p>\n<p>57' 《月光》<br />\n好温柔的歌</p>\n<p>1h10min 日文歌（p.s. ひまわりの約束（中日混 ver.）</p>\n<p>1h17min 很火的一首水歌（一直以为是英文歌来着（小城夏天</p>\n<p>1h22min 《看月亮爬上来》<br />\n跟不上歌，原唱到 “没我可怎么办” 的时候兔兔：“是啊，我可怎么办”<br />\n 兔：“失眠的夜就有人向你告白，那得有多少人向你告白啊”</p>\n<p>1h31min 《借青春》<br />\n温柔的歌，不过不知道为啥，在手机上听更有感觉</p>\n<p>1h34<br />\n 第三次厕所<br />\n咳咳咳，什么也没听见</p>\n<p>1h42min 《朋友（魔豆传奇）》<br />\n这首特别可爱⚈₃⚈</p>\n</div></details>\n<h2 id=\"信息整理\"><a class=\"anchor\" href=\"#信息整理\">#</a> 信息整理</h2>\n<ul>\n<li><span class=\"exturl\" data-url=\"aHR0cHM6Ly93ZWliby5jb20vNjcwNDIxNjQyMS9NNmRHVDNSUDU=\">林予曦歌会名录（K 站 + M 站）</span></li>\n</ul>\n<h2 id=\"一些相关网站\"><a class=\"anchor\" href=\"#一些相关网站\">#</a> 一些相关网站</h2>\n<p><div class=\"links\"><div class=\"item\" title=\"林予曦\"><span class=\"exturl image\" data-url=\"aHR0cHM6Ly93d3cubWlzc2V2YW4uY29tL3NlaXkvMTMxMg==\" data-background-image=\"https://static.maoercdn.com/seiys/201906/06/5b0f4b37ef97bca89fd4b2d30db34f95173358.jpg\"></span>\n          <div class=\"info\">\n          <span class=\"exturl title\" data-url=\"aHR0cHM6Ly93d3cubWlzc2V2YW4uY29tL3NlaXkvMTMxMg==\">林予曦-决意同人</span>\n          <p class=\"desc\">猫耳FM：剧集</p>\n          </div></div><div class=\"item\" title=\"虞美人小蜜\"><span class=\"exturl image\" data-url=\"aHR0cHM6Ly93d3cubWlzc2V2YW4uY29tL21kcmFtYS8zMzY5MA==\" data-background-image=\"/images/404.png\"></span>\n          <div class=\"info\">\n          <span class=\"exturl title\" data-url=\"aHR0cHM6Ly93d3cubWlzc2V2YW4uY29tL21kcmFtYS8zMzY5MA==\">林予曦（兔兔）歌曲不完全合集</span>\n          <p class=\"desc\">猫耳FM：歌曲单截</p>\n          </div></div><div class=\"item\" title=\"娜娜很机智，季夏有木兮。\"><span class=\"exturl image\" data-url=\"aHR0cHM6Ly93d3cubG9yaW5seXguY29tLw==\" data-background-image=\"/images/404.png\"></span>\n          <div class=\"info\">\n          <span class=\"exturl title\" data-url=\"aHR0cHM6Ly93d3cubG9yaW5seXguY29tLw==\">与曦同行｜林予曦个人网站</span>\n          <p class=\"desc\">予兔同行，温暖如曦</p>\n          </div></div></div></p>\n",
            "tags": [
                "广播剧",
                "声优",
                "声优"
            ]
        },
        {
            "id": "https://sneexy.github.io/2022/08/27/drama/%E3%80%90%E6%B8%85%E6%B3%89-Sneexy%E3%80%912022%E5%B9%BF%E6%92%AD%E5%89%A7%E5%90%AC%E5%89%A7%E8%AE%B0%E5%BD%95/",
            "url": "https://sneexy.github.io/2022/08/27/drama/%E3%80%90%E6%B8%85%E6%B3%89-Sneexy%E3%80%912022%E5%B9%BF%E6%92%AD%E5%89%A7%E5%90%AC%E5%89%A7%E8%AE%B0%E5%BD%95/",
            "title": "【清泉/Sneexy】2022广播剧听剧记录",
            "date_published": "2022-08-27T06:30:07.000Z",
            "content_html": "<h1 id=\"清泉sneexy2022广播剧听剧记录\"><a class=\"anchor\" href=\"#清泉sneexy2022广播剧听剧记录\">#</a> 【清泉 / Sneexy】2022 广播剧听剧记录</h1>\n<h2 id=\"总结\"><a class=\"anchor\" href=\"#总结\">#</a> 总结</h2>\n<ul>\n<li>好听剧，不求甚解，每有会意，便欣然忘眠</li>\n<li>受控，喜欢女王受、美人受、软糯受、萌受……</li>\n<li>喜虐，be 美学爱好者，糖可能是一时的，但刀是一世的</li>\n<li>杂食系，喜欢一个人就逮着经典作代表作薅</li>\n<li>不论剧评，感谢每一部剧的 SC</li>\n<li><span class=\"spoiler\" title=\"你知道得太多了\">感谢豆瓣这么垃圾，治好了我的强迫症</span></li>\n</ul>\n<h2 id=\"时间线\"><a class=\"anchor\" href=\"#时间线\">#</a> 时间线</h2>\n<ol>\n<li>《破云》入坑天空，开始了对天空的漫漫考古路。</li>\n<li>《法外之徒》入坑林予曦，断断续续听。</li>\n<li>《吞雨》入坑矜持 ING，考古代表作，一堆未完结。</li>\n<li>《困流》入坑陈小 C，考古代表作。</li>\n<li>补一些 mark 的剧</li>\n</ol>\n<h2 id=\"墙头们\"><a class=\"anchor\" href=\"#墙头们\">#</a> 墙头们</h2>\n<p>本命天空 &amp; 陈小 C，墙头（专注作品，时间顺序）：</p>\n<ul>\n<li>旧旧墙头：神谷浩史，平川大辅，下野纮，野岛健儿，武内健</li>\n<li>旧墙头：羊仔、倒霉死勒</li>\n<li>今年的新墙头 ：\n<ul>\n<li>林予曦。软糯又带点气质，很适合配有个性的角色，倨傲或乖顺忍耐的都好。选剧本不太行。唱歌好听。没有偶像包袱，剧里该破音就破音 hhh</li>\n<li>糖醋排骨。戏路广，演技很好，很贴角色，能配出角色的复杂性。戏外又很萌 。唱歌好听</li>\n<li>矜持 ING。声音有种魅惑的美。笑起来很好听。eng 总读成 en。</li>\n<li>陈小 C。现在叫陈想先生。声音的底色像玉一样，演技很好，很多情绪个性都能拿捏，淡淡的但也挺自然。配虐剧很有感觉，傲娇闷骚矜贵冰冷腹黑美强惨专业户。比林予曦攻多了。po 总读成 pe，bo 总读成 be。（升级了）</li>\n</ul>\n</li>\n</ul>\n<h2 id=\"听剧列表\"><a class=\"anchor\" href=\"#听剧列表\">#</a> 听剧列表</h2>\n<h3 id=\"格式\"><a class=\"anchor\" href=\"#格式\">#</a> 格式</h3>\n<p>《作品名》主役：评分（期数）<br />\n【听完日期】主角；评论（剧情，配音，制作）。<br />\n紫：n 刷。蓝：四星 +。黄：不更。</p>\n<h3 id=\"完结不更\"><a class=\"anchor\" href=\"#完结不更\">#</a> 完结 / 不更</h3>\n<h4 id=\"1-50\"><a class=\"anchor\" href=\"#1-50\">#</a> 1-50</h4>\n<details class=\"info\"><summary>《不法之徒》天空X朴枫：★★★★（5）</summary><div>\n<ul>\n<li>【22.1.12】主角：齐修远 X 萧厉</li>\n<li>第一次偏爱攻多过受。</li>\n<li>齐修远这口才这头脑不去兼职语文老师可惜了，而且很坚持，很体贴，很勇敢，因为他觉得值得，所以不愿意让萧厉觉得是亏欠了自己</li>\n<li><span class=\"spoiler\" title=\"你知道得太多了\">齐修远：我最喜欢听你说：“齐修远，你别这样”。</span></li>\n</ul>\n</div></details>\n<details class=\"success\"><summary>《蘑菇炒鱿鱼》天空X李逍遥：★★★☆（3）</summary><div>\n<ul>\n<li>【22.1.16】主角：邵友名 X 绉飞</li>\n<li>考古。沙雕。</li>\n<li>天空在沙雕中还是有点气质的。</li>\n<li>糖醋排骨女王受（雷粤），小小的又有点可爱。</li>\n</ul>\n</div></details>\n<details class=\"success\"><summary>《蓝波万》天空X乘风归去：★★★☆（3）</summary><div>\n<ul>\n<li>【22.1.21】主角：张千 X 李万</li>\n<li>搞笑剧。</li>\n<li>天空的弱攻挺萌的</li>\n</ul>\n</div></details>\n<details class=\"warning\"><summary>[不更]《提灯看刺刀》AaronX卡修（1）</summary><div>\n<ul>\n<li>【22.1.23】主角：韩越 X 楚慈</li>\n</ul>\n</div></details>\n<details class=\"primary\"><summary>《法外之徒》古月三刀X林予曦：★★★★（2）</summary><div>\n<ul>\n<li>【22.1.24】主角：罗聿 阮争 / 苏家文</li>\n<li>故事本身没有很吸引人，但是林予曦塑造出来的这个角色我很喜欢。像武内健一样的小白兔，入坑林予曦</li>\n</ul>\n</div></details>\n<details class=\"info\"><summary>《貌合神离》燃X林予曦：★★★★（3）</summary><div>\n<ul>\n<li>【22.1.28】主角：季明轩 X 沈默</li>\n<li>剧情也不吸引人，但是喜欢林予曦的声音。<span class=\"spoiler\" title=\"你知道得太多了\">咳咳</span>  <span class=\"spoiler\" title=\"你知道得太多了\">第三期念白那里的层次感很绝呀</span></li>\n</ul>\n</div></details>\n<details class=\"info\"><summary>《我把你当兄弟》倒霉死勒X糖醋排骨：★★★★（13+4）</summary><div>\n<ul>\n<li>【22.02.13】主角：许熙然 X 方默</li>\n<li>除了第一话有点乱，后面都比较搞笑了。一环套一环的，每次方默露一点陷或下个套，都能被许熙然圆回来 hhh，误会搞笑得很巧妙。</li>\n<li>方默声线又气质又俏皮。<span class=\"grey\">差不多从这时候入坑糖醋排骨，加上《义父》里的叶崇义，每次塑造谁就是谁</span></li>\n</ul>\n</div></details>\n<details class=\"success\"><summary>《谁把谁当真》番外篇《假如》天空，木野信：★★★☆（1）</summary><div>\n<ul>\n<li>主角：黎朔，赵锦辛</li>\n<li>很多年前，阳光的黎朔和可爱的赵锦辛</li>\n</ul>\n</div></details>\n<details class=\"success\"><summary>《乡村教师》遥远，天空：★★★（1）</summary><div>\n<ul>\n<li>【22.02.15】</li>\n<li>故事情节有些简单，感慨有些空</li>\n</ul>\n</div></details>\n<details class=\"warning\"><summary>[不更]《颊边痣》风允之X林予曦：★★★☆（2）</summary><div>\n<ul>\n<li>【22.02.28】主角：魏德永 X 许锥儿</li>\n<li>看着标题挺秀气，结果是土土的方言风格。</li>\n<li>不过林予曦配的锥儿笑起来真是又土又可爱。</li>\n<li>花絮有毒哈哈 <span class=\"exturl\" data-url=\"aHR0cHM6Ly93d3cubWlzc2V2YW4uY29tL3NvdW5kL3BsYXllcj9pZD0xMDA1Mzk5\">《颊边痣》现场之两位娘娘的相声表演</span></li>\n</ul>\n</div></details>\n<details class=\"info\"><summary>《水魅》笑谈X天空：★★★★（5）</summary><div>\n<ul>\n<li>【22.3.2】主角：水珄 X 徐离晟</li>\n<li>对天空演绎的女王受毫无抵抗力，敢爱敢恨优秀强大果断，知道自己想要什么，知道怎么保护自己爱的人，非常拎得清 ，简直就是完美人设。</li>\n<li>徐离晟： “我为什么要内疚， 你喜欢我， 为我做任何事都是应该的， 就像我喜欢你， 也会为你做任何事， 不惜代价。”</li>\n</ul>\n</div></details>\n<details class=\"primary\"><summary>《想你的张青凯》唱油条，天空：★★★★☆（1）</summary><div>\n<ul>\n<li>【22.03.09】主角：张青凯，夏飞</li>\n<li>很紧凑，细节很多，情绪到位，很有真实感。唯一缺点是太短，听不够</li>\n<li>回忆里的夏飞很温柔，又有小任性，意难平。</li>\n</ul>\n</div></details>\n<details class=\"warning\"><summary>[不更]《吞雨》风允之X矜持ING：★★★★（4）</summary><div>\n<ul>\n<li>【22.03.21】主角：谢桥 X 纪真宜</li>\n<li>年轻时候的谢桥还会生硬地撒娇、伤心了还哭哭啼啼，刷新了我对攻的认知；矜持配的纪真宜，随性又主动，自然而诱惑，刷新了我对受的认知</li>\n</ul>\n</div></details>\n<details class=\"success\"><summary>《就是图个乐儿》天空、冬冬、风雨归舟、一天、朴枫、永无乡de宁静：★★★☆（1）</summary><div>\n<ul>\n<li>【22.3.26】</li>\n<li>小短剧，挺逗的。</li>\n<li><span class=\"spoiler\" title=\"你知道得太多了\">沙雕骚气版冬冬</span></li>\n</ul>\n</div></details>\n<details class=\"info\"><summary>《后来》天空，库络里多，永无乡の宁静，沈二然：★★★★（2）</summary><div>\n<ul>\n<li>【22.3.27】主角：孔新，陈夏</li>\n<li>关于错过，意难平。</li>\n<li>上期不怎么吸引人。</li>\n<li>京片子。</li>\n</ul>\n</div></details>\n<details class=\"success\"><summary>《伴儿》可乐冰，Forsaken：★★★☆（1）</summary><div>\n<ul>\n<li>【22.3.28】主角：丁当，孔越</li>\n<li>《后来》的后续，孔新弟弟的故事。</li>\n<li>孔越这小嘴叭叭个没停，还挺可爱的。送伞那段冲突有点感人。</li>\n<li>天空协役，孔新陈夏还是没有好的结果，为了上一辈眼里表面的幸福而让两个人都不幸福</li>\n</ul>\n</div></details>\n<details class=\"success\"><summary>《影子》一天，千明：★★★（1）</summary><div>\n<ul>\n<li>【22.4.2】主角：林影，张晗</li>\n<li>《后来》同一个系列。</li>\n<li>双向暗恋。</li>\n<li>千明和小随音色好像。在 28min55s 处语速惊人。可乐冰声音好嫩。天空客串</li>\n</ul>\n</div></details>\n<details class=\"info\"><summary>《共生》倒霉死勒X羊仔：★★★★（2）</summary><div>\n<ul>\n<li>【22.4.4】主角：陆久 X 柴东东</li>\n<li>剧如其名，挺压抑的，爱恨交织。避免剧透最好盲听，声音很清楚。 “陆久拿你真好三个字绑了东东一辈子”</li>\n<li>配音也不错，情绪的递进到位，羊仔的哭戏好。</li>\n</ul>\n</div></details>\n<details class=\"success\"><summary>《男男之间》八千里路X林予曦：★★★（4）</summary><div>\n<ul>\n<li>主角：彭智然 X 陈嘉</li>\n<li>听得挺累的，前期受情绪太敏感，后期的冲突又是老梗。</li>\n<li>音量忽大忽小，bgm 忽大忽小</li>\n<li>ed 都是林予曦唱的，还不错</li>\n</ul>\n</div></details>\n<details class=\"success\"><summary>《俗不可耐》天空X可乐冰：★★★☆（4）</summary><div>\n<ul>\n<li>【22.4.7】主角：庄洁 X 颜卿</li>\n<li>备胎的卑微故事，挺难的，但又是自找的。庄洁对齐小冰和对颜卿的态度挺讽刺的，他不是不会把人捧在手心，只是那个人不是你罢了。</li>\n<li>可乐冰、天空、一天配得挺好。</li>\n</ul>\n</div></details>\n<details class=\"warning\"><summary>[不更]《臣服Ⅱ》燃X林予曦（2）</summary><div>\n<ul>\n<li>【22.4.12】主角：方明衍 X 卓悦</li>\n<li>上次更新 2017，应该坑了。</li>\n</ul>\n</div></details>\n<details class=\"success\"><summary>《摄魂》漠然：★★★☆（1）</summary><div>\n<ul>\n<li>【22.4.13】主角：穆晨</li>\n<li>故事很短，都是一些碎片。</li>\n<li>氛围有点吓人。</li>\n<li>给里面天空的四种角色状态加半颗星</li>\n</ul>\n</div></details>\n<details class=\"success\"><summary>《J禁》上官佑X小K：★★★（1）</summary><div>\n<ul>\n<li>【22.4.13】主角：文雪岸 X 叶告；</li>\n<li><span class=\"spoiler\" title=\"你知道得太多了\">有车无剧情</span></li>\n</ul>\n</div></details>\n<details class=\"success\"><summary>《你可曾见过如此高冷的作者》天空X林予曦：★★★（11）</summary><div>\n<ul>\n<li>【22.4.14】主角：路敛光 X 唐簇</li>\n<li>剧情和人物都很平，唐簇的妈刻画得不合理的疯。到后期只能当背景听。</li>\n<li>番外的副 cp 比较有感觉。</li>\n<li>ft 挺甜。</li>\n</ul>\n</div></details>\n<details class=\"warning\"><summary>[不更]《假面》楼生/远岸云收X矜持ING：★★★☆（2）</summary><div>\n<ul>\n<li>【22.4.14】主角：邱文明 X 沈慈</li>\n<li>上次更新 2015，应该坑了</li>\n<li>女装受，听到矜持的伪音去听的。矜持声音很美，也很放得开，入坑了。</li>\n<li>除开声音，故事本身不太吸引我，一个因为被伤害过而有了女装癖和受虐倾向的人，还要被伤害去治愈一个被别人伤害的人，攻脾气太差了。</li>\n</ul>\n</div></details>\n<details class=\"primary\"><summary>《困流》阿册/HolyNightX陈小C：★★★★★（5）</summary><div>\n<ul>\n<li>【22.4.15】主角：周鸿 X 谭清泉</li>\n<li>“周鸿认为：‘我要困住他，不能只用爱情。’ 他小心地用各种感情、金钱、权利、人脉，竖起一堵堵看不见的高墙，无论谭清泉在哪里，都离不开这个人。谭清泉是淡漠而随遇而安的流水，周鸿费尽心机，还是将流水困住了。”</li>\n<li>角色个性挺立体，人物行为基于个人经历，剧情、编剧、配音和后期都很给力。很清醒的互相利用的强强，对谭这种冷淡的美强惨，只能攻心了，一步步攻心的过程挺有意思的，周背着谭心狠手辣，对着他又体贴入微，既是地狱也是救赎。</li>\n<li>听了一段矜持的本剧 cut 来听的。矜持 ING、冬冬协役，乘风龙套。被陈小 C 声音迷住了，每一句话都值得反复听，细微的情绪差别让人物很生动。刘思问谭透过自己在看谁，他的一句 “妈妈” 出神而眷恋，这里改编和配音太棒了。</li>\n<li>最近听了好几部无字幕，当练中文听力了。</li>\n</ul>\n</div></details>\n<details class=\"success\"><summary>《友谊的小船，说翻就翻》陈小C X 林予曦：★★★☆（1）</summary><div>\n<ul>\n<li>【22.4.19】主角：蛇精荀乐 X 兔子精涂之</li>\n<li>池袋最强原著。无脑小甜饼。挺 Q 的，兔兔配了兔兔。</li>\n<li>陈小 C 声音好听</li>\n</ul>\n</div></details>\n<details class=\"success\"><summary>《一分钟教你人肉搜索》桃吉贰 X 静水，轩ZONE X 水无涯/呆呆Akuma：★★★☆（1）</summary><div>\n<ul>\n<li>【22.4.20】</li>\n<li>吐维原著推理剧，小说挺出名</li>\n<li>桃吉贰、呆呆 Akuma 淡淡的声线好听。轩 ZONE 的哭戏有感染力。</li>\n</ul>\n</div></details>\n<details class=\"success\"><summary>《冥府之路》雅策君X矜持ING：★★★☆（2）</summary><div>\n<ul>\n<li>【22.4.21】主角：雷子 X 关慧良</li>\n<li>听了这个<span class=\"exturl\" data-url=\"aHR0cHM6Ly93d3cuYmlsaWJpbGkuY29tL3ZpZGVvL0JWMUhKNDExWTdOMQ==\"> cut</span>，来听矜持 ING 的哭腔、哭喊、恐惧的声音。</li>\n<li>绑架案，故事一般。“QQ 微信都得删除，给你留个网易云音乐吧”，作者为了推动情节真是哈哈哈。</li>\n<li>雷子说仁义也仁义，说冲动也太冲动。这也算一个法外之徒吧。</li>\n</ul>\n</div></details>\n<details class=\"warning\"><summary>[不更]《YJ男的春天》木津川X矜持ING（1）</summary><div>\n<ul>\n<li>【22.4.21】主角：连旗 X 禾苗</li>\n<li>上次更新 2015，应该坑了。情节才刚开始。</li>\n<li>老早就听了矜持 ING 的《套马杆》，很妖媚，原来是这个的 ed。剧里又哭了。还挺毒舌嘴炮。</li>\n</ul>\n</div></details>\n<details class=\"info\"><summary>《我只要你》轩辕靖日X陈小C：★★★★☆（3）</summary><div>\n<ul>\n<li>【22.4.22】主角：廖维信 X 白既明</li>\n<li>《困流》同一个原作者。剧本也写得挺紧凑，几分钟就能交代背景，几分钟就能把情节刻画好。</li>\n<li>现实向。看上去是廖低声下气死缠烂打，白既明理智得冷冰冰，但白冒着家庭和工作上的风险，接受这段感情需要更大的决心，好在廖对他挺好的。</li>\n<li>白既明理智、天真、活泼、诱惑、颐指气使、傲娇、冷淡、毒舌、撒娇、使坏、自责、委屈、喝醉、懵愣、乖巧的状态被陈小 C 配得很好，开心的时候小尾巴能翘到天上，一看就是被家里和廖宠得很。</li>\n<li>陈小 C 代表作。如果《俗不可耐》里的齐小冰是陈小 C 的声音，不是不能理解为什么庄洁和周瑾只把齐小冰捧在手里怕摔了，含在嘴里怕化了。大概这就是纯欲吧，开头一句 “去你那里好吗” 挺勾人的。听了陈小 C 的几部剧了，对这声音是一听钟情吧。</li>\n</ul>\n</div></details>\n<details class=\"warning\"><summary>[不更]《二进制》正经太郎X陈小C：★★★★（4）</summary><div>\n<ul>\n<li>【22.4.23】主角：韩敬 X 兰知</li>\n<li>上次更新 2016，<ins>可能</ins>坑了。</li>\n<li>韩有点憨憨的，略粗俗。兰知清冷美人女王受，只是说话就很好听，带着情绪更动人。陈小 C 专业配闷骚。</li>\n<li>故事一般</li>\n</ul>\n</div></details>\n<details class=\"primary\"><summary>《桃魅》风允之X陈小C：★★★★☆（4）</summary><div>\n<ul>\n<li>【22.4.24】主角：杨桃 X 仲廷玉</li>\n<li>古风。虐得很，又是美强惨，因为美而一直受苦，空有才华却用来报复；另一方面他又确实阴险狠辣，恃宠而骄，结党营私，做乱臣贼子让百姓难过。他对自己狠，对狗皇帝狠，对天下苍生狠，只把温柔留给了杨桃。狗皇帝机关算尽，只把感情给了仲廷玉，却从没对他温柔。</li>\n<li>陈小 C 配得很贴，甚至青出于蓝胜于蓝，第四期伤了皇帝后的话和笑表现得很惊艳。</li>\n<li>边虐还边穿插些搞笑。番外和 ft 也努力让大家走出来，方言 pia 戏声优都不贵了，东北大汉美人儿。第四期 ed 里小 C 唱歌声音挺攻的。</li>\n</ul>\n</div></details>\n<details class=\"info\"><summary>《姑妄听之》轩辕靖日X陈小C：★★★★（1）</summary><div>\n<ul>\n<li>【22.4.25】主角：相南王 X 小皇帝，富商 X 书生</li>\n<li>古风全一期，一半虐一半甜。</li>\n<li>陈小 C 的声音真好听，特别是弥留之际那一段。</li>\n</ul>\n</div></details>\n<details class=\"success\"><summary>《我被我想要追的女孩的哥哥追到手了》守护X夜汐：★★★（1）</summary><div>\n<ul>\n<li>【22.4.26】主角：秋木 X 刘哲宇</li>\n<li>见标进。故事挺简单的。</li>\n</ul>\n</div></details>\n<details class=\"success\"><summary>《一个人的绅士》羊仔X陈小C：★★★☆（1）</summary><div>\n<ul>\n<li>【22.4.26】主角：绅士 X 男友</li>\n<li>全一期小短剧。攻音羊仔，羊仔攻了！（花絮就受了）这么短竟然还有车。</li>\n</ul>\n</div></details>\n<details class=\"success\"><summary>《都是赖床惹的祸》陈小C X 小坠：★★★☆（1）</summary><div>\n<ul>\n<li>【22.4.26】主角：快递小哥 X 赖床君</li>\n<li>小坠的脑洞，他唱的 ed 也很萌。</li>\n<li>小坠好会撒娇好会卖萌，竟然对陈美人撒娇。小 C 攻了！</li>\n</ul>\n</div></details>\n<details class=\"success\"><summary>《喜欢你》鲨鱼X陈小C：★★★☆（1）</summary><div>\n<ul>\n<li>【22.4.27】主角：蒋云航 X 庄柳</li>\n<li>呆萌小 C。撒娇太可爱了</li>\n<li>bgm 声音太大，不过瑕不掩瑜</li>\n</ul>\n</div></details>\n<details class=\"success\"><summary>《未亡人》鲨鱼X陈小C：★★★（1）</summary><div>\n<ul>\n<li>【22.4.27】主角：周学长 X 小夏</li>\n<li>扶他柠檬茶原著，扶他 + 陈小 C = 虐。虽然小夏是女装大佬，但是剧情中不明显，可不得像《假面》里矜持那样伪音一下。周学长是个老好人了，接受他的爱好，还替他摆平恶意，心动就是一个个瞬间。</li>\n</ul>\n</div></details>\n<details class=\"info\"><summary>《罂粟》魅影之声X陈小C：★★★★（1）</summary><div>\n<ul>\n<li>【22.4.27】主角：唐孝嘉 X 卢凤楼</li>\n<li>陈小 C 的女王受，敢爱敢恨，有杀伐决断，放在民国背景下更带感了。姐姐的 CV 祁司 somli 的御姐音也很好听。</li>\n<li>结局很巧妙，他重要的人怀疑他，主动与他拼个你死我活，结果都死在他手上，所以这一次他毫不犹豫，然后说 “你要死在我后面”。</li>\n</ul>\n</div></details>\n<details class=\"info\"><summary>《煎饼车》卡修X林予曦，江笙X羊仔：★★★★（2）</summary><div>\n<ul>\n<li>【22.4.29】主角：尹良 X 陆路，地藏 X 黄海</li>\n<li>听了 cut 来的。认真在搞笑，四个戏精。陆路这个沙雕套路诱受，摊牌时还能中二霸总一回（虽然没有气势，想 rua）；装小白兔的设定，想起了法外之徒。<span class=\"spoiler\" title=\"你知道得太多了\">兔兔和羊仔的在线煎饼车</span>。</li>\n</ul>\n</div></details>\n<details class=\"info\"><summary>《最爱你的那十年》商桐X尘霜满眸：★★★★（4）</summary><div>\n<ul>\n<li>【22.4.30】主角：蒋文旭 X 贺知书</li>\n<li>“但是，蒋文旭，爱没有了，我还能在你身边留多久。”</li>\n<li>两个人的哭戏都挺不错</li>\n</ul>\n</div></details>\n<details class=\"success\"><summary>《双生梅》天空X倔强的小红：★★★☆（1）</summary><div>\n<ul>\n<li>【22.5.5】主角：韩仲珂 X 罗云生</li>\n<li>民国 be 剧。声音好听，但是总觉得剧里表现的羁绊不够深，怎么能记得了 30 年。</li>\n</ul>\n</div></details>\n<details class=\"success\"><summary>《我只是来送货的呀》墨千临X矜持ING：★★★☆（1）</summary><div>\n<ul>\n<li>【22.5.6】主角：收货员 X 送货员；</li>\n<li><span class=\"spoiler\" title=\"你知道得太多了\">有车无剧情</span></li>\n</ul>\n</div></details>\n<details class=\"info\"><summary>《狼狗》柳凄X顾辰：★★★★（2）</summary><div>\n<ul>\n<li>【22.5.8】主角：池又鳞 X 池亦溟</li>\n<li>七姐 Claudia 推荐。偏执的占有欲，带感。</li>\n<li>两个 CV 的声音都好听。不过车的时候顾辰好像变娇了（虽然也好听）。</li>\n</ul>\n</div></details>\n<details class=\"success\"><summary>《地下室SM实录》煜煊X矜持ING：★★★（1）</summary><div>\n<ul>\n<li>【22.5.9】主角：谢家辰 X 贺哲</li>\n<li>标题党，其实是双向暗恋小甜剧。攻的嘴白长了，老是用 “你到底想怎样” 询问对方的想法，把受气得哦。</li>\n</ul>\n</div></details>\n<details class=\"success\"><summary>《高级定制》江笙X Mr.岑：★★★☆（2）</summary><div>\n<ul>\n<li>【22.5.9】主角：秦彧 X 文清</li>\n<li>最近听多了岑岑灯的《天生一对》就想听听岑岑的伪音剧。虽然本音弱一些，但御姐音就是大美女，带刺的玫瑰～。ed《我的世界》by Mr. 岑。 这个剧倒像是给岑岑的高级定制了。</li>\n<li>原创剧。剧情还行但感觉有 bug，能跑为啥不带秦一起跑</li>\n</ul>\n</div></details>\n<details class=\"success\"><summary>《痛感》夙七烈X陈小C：★★★☆（1）</summary><div>\n<ul>\n<li>【22.5.10】主角：奉远城 X 原天波</li>\n<li>平平淡淡的一个因为误会相识的故事，配得很自然，有生活感。</li>\n<li>ED 是龙牙翻唱的《你是我的风景》，V 曲，调教得挺好</li>\n</ul>\n</div></details>\n<details class=\"success\"><summary>《公园之夜》墨千临X妖仙：★★★（1）</summary><div>\n<ul>\n<li>【22.5.13】主角：刘康 X 顾颜</li>\n<li><span class=\"spoiler\" title=\"你知道得太多了\">有车无剧情</span></li>\n</ul>\n</div></details>\n<details class=\"info\"><summary>《七年止痒》杨东旭X天空：★★★★（1）</summary><div>\n<ul>\n<li>【22.5.13】主角：张任 X 邓贤</li>\n<li>超长全一期搞笑剧，时而搞笑时而甜的，谐音梗密集。</li>\n<li>天空久违的京味儿的攻音受，会撒娇的年上。协役也比较搞笑，唱油条，八千里路，风华无双。ed《爱着爱着就永远》，主役合唱，之前听过很多遍。</li>\n</ul>\n</div></details>\n<h4 id=\"现场pia戏\"><a class=\"anchor\" href=\"#现场pia戏\">#</a> 现场 pia 戏</h4>\n<details class=\"success\"><summary>目录</summary><div>\n<ul>\n<li>《缝纫机之恋》顾辰 X 矜持 ING</li>\n<li>《当杀手接到了骚扰电话》6 熙 X 矜持 ING</li>\n</ul>\n</div></details>\n<h4 id=\"51-\"><a class=\"anchor\" href=\"#51-\">#</a> 51-</h4>\n<details class=\"info\"><summary>《坏故事之监禁》心外無物，雅策君：★★★★（1）</summary><div>\n<ul>\n<li>【22.5.13】主角：林志，叶杰</li>\n<li>单箭头的爱，疯狂的迷恋，爆发的占有欲，编织的谎言，从天堂到地狱。叶摆脱的是束缚，也是无条件的、事无巨细的 “我好爱你”，从他闪耀的少年时代，到他发福谢顶被生活摧残到没有激情。</li>\n<li>心外無物配得很好，自己的爱被看到时的激动兴奋，语速也变快，能听出他眼里的光；非常小心翼翼，卑微，只要叶愿意他能付出一切。因为占有欲而疯狂，语无伦次，蹦出来的话沾上了很浓烈的感情。</li>\n</ul>\n</div></details>\n<details class=\"success\"><summary>《社交温度》倔强的小红军X林予曦：★★★☆（6）</summary><div>\n<ul>\n<li>【22.5.15】主角：宋远旬 X 方昭暮</li>\n<li>兔兔声音很软，可爱，他跟 Andrew 说话真的好甜。 “你的喜欢值钱，我的喜欢不值，我给 Andrew 的喜欢呢，我去找谁要回来啊？” 听到这里的哭腔就能体会方的伤心了，心疼。</li>\n<li>不太喜欢的点是，最开始宋误会方抢了他朋友的交换名额、以及觉得他娘而带头孤立他，又因为喜欢他才在现实中缓和关系。另外，方在国内有那么多朋友，不至于只能找 Andrew 倾诉吧。</li>\n<li>3 话弃了，猫耳上架又捞起来下饭了，听了宋的解释好像又能接受了。故事整体还是有点别扭。</li>\n</ul>\n</div></details>\n<details class=\"warning\"><summary>[不更]《关河令》陈小C X 矜持ING：★★★☆（1）</summary><div>\n<ul>\n<li>【22.5.16】主角：毓弋 X 怜更</li>\n<li>非常古早，听得不清晰。不过故事和矛盾已经铺垫出了，画面感也比较足。感觉是虐剧。</li>\n<li>陈小 C 攻，锦鲤攻</li>\n<li>番外《客官不可以》矜持 ING 饰 250 小倌，陈小 C 饰妖娆小倌，向以辰饰倒霉嫖客。听了很多遍。六分钟的小短番外。陈小 C 和矜持 ING 是够妖娆和沙雕的，<span class=\"spoiler\" title=\"你知道得太多了\">听矜持叫妈妈</span>。</li>\n</ul>\n</div></details>\n<details class=\"success\"><summary>《你是人间小甜饼》 HolyNight X 陈小C：★★★（2）</summary><div>\n<ul>\n<li>【22.5.18】主角：沈知忧 X 顾若白</li>\n<li>说好的小甜饼呢，不太甜。而且剧情到后面就越来越迷了，只是上下期却塞了太多东西，弹幕吐槽：“干嘛不说？别问，问就是作者不让”、“校园文变黑道文”。</li>\n</ul>\n</div></details>\n<details class=\"info\"><summary>《疯子》Mr.岑 X 心外無物：★★★★（1）</summary><div>\n<ul>\n<li>【22.5.21】主角：兔 X 叶梓</li>\n<li>超长全一期。剧如其名，越听到后面越疯越带感越压抑。从兔读诗的那段开始，故事推向高潮，听完有点难受。（这首诗感觉以前在哪里听过，唱的或者很 drama 的形式念的）</li>\n<li>心外無物的戏感很好，Mr. 岑配病娇的时候比一般的男声时好一些。</li>\n</ul>\n</div></details>\n<details class=\"info\"><summary>《年少与妖娆》唱油条 X 陈小C：★★★★☆（5）</summary><div>\n<ul>\n<li>【22.5.23】主角：易坤 X 卓影</li>\n<li>剧情、人设、后期都挺带感。黑道背景，女王受 &amp; 忠犬攻。反转很多。结局还挺欣慰的，他们都守住了自己的承诺。易坤看着呆呆的，最后其实是在炫耀他赢了吧，所以卓影才嘴硬。</li>\n<li>《年少与妖娆》指《Young and Beautiful》，其实为了《破云》的 “仲夏初茫，七月未央” 就听过很多遍这首歌，但是他们之间没有双向的感情，只有执念和憎恨。而这部剧里这首歌作为插曲和 ed，更为贴切，虽然 be 了，他们自始至终是愿意为对方付出生命的，比黛西和盖茨比的感情更动人，每一期分隔得刚刚好，ed 所承载的情绪不一样。</li>\n<li>整部剧主协役龙套的戏感大部分都挺好，声音也好听（俩主役的声音让人心动，听习惯了才被拉回剧情（可能也有张青凯的滤镜在））。卓影的妖媚、女王、A、深情，易坤的忠诚、木讷、木讷地撒娇都挺好，而且不同心境下的变化也表现得很好。还有轩辕靖日、魅影之声、HolyNight、十二月等，续续点灯报幕。</li>\n</ul>\n</div></details>\n<details class=\"warning\"><summary>[不更]《好学的江帆》续续点灯 X 风允之：★★★☆（1）</summary><div>\n<ul>\n<li>【22.5.25】主角：杜君棠 X 江帆</li>\n<li>剧情和虐主要在下期，下期不更了这部的主题就变了。</li>\n<li>没想到你是这样的续续。没想到你是这样的大风，受起来确实不一样，而且也过于放得开了（捂脸）。</li>\n</ul>\n</div></details>\n<details class=\"success\"><summary>《当我用灵魂和恶魔做了交易之后》擎苍，星潮：★★★☆（1）</summary><div>\n<ul>\n<li>【22.5.26】主角：恶魔，小王</li>\n<li>扶他柠檬茶原著，沙雕中二。把灵魂献给了恶魔，恶魔却让他认真学习、多吃青菜、坚持锻炼，从而实现统治世界的中二目标，恶魔跟个男妈妈一样，结局变小了好萌。</li>\n</ul>\n</div></details>\n<details class=\"info\"><summary>《泥中の蓮》小林裕介 X 増田俊樹：★★★★（6）</summary><div>\n<ul>\n<li>主角：元春 X 秋生</li>\n<li>第 1、3 话弟弟视角，第 2、4 话哥哥视角。这哥哥一直是白切黑啊并不突兀，发现弟弟要上大学了就以退为进使了激将法，扮演好哥哥。人设比较特别</li>\n</ul>\n</div></details>\n<details class=\"success\"><summary>《Python入门指南》炒肉君 X 庄十三：★★★（2）</summary><div>\n<ul>\n<li>【22.5.27】主角：付行文 X 程絮</li>\n<li>略搞笑略小甜饼，跟 Python 顶多到把 “Py 交易” 胡解释成 “卖 Python 课程” 的关系</li>\n</ul>\n</div></details>\n<details class=\"warning\"><summary>《三十而受》阎摩 X 陈小C：★★★☆（2）</summary><div>\n<ul>\n<li>【22.6.5】主角：石磊 X 沈闲</li>\n<li>对做攻非常自信的花花公子，然后因为心软受了。台词烫嘴。很少见小 C 配这种形象，挺喜欢这种游刃有余的劲儿的。</li>\n</ul>\n</div></details>\n<details class=\"success\"><summary>《小弟与黑道大哥》笑意 X 冬冬：★★★☆（1）</summary><div>\n<ul>\n<li>【22.6.22】主角：小弟 X 大哥</li>\n<li>沙雕搞笑剧。大哥是 “嘤嘤嘤版张飞” 和小说角色扮演爱好者的结合。台词略烫嘴。</li>\n</ul>\n</div></details>\n<details class=\"info\"><summary>《死对头是猫薄荷而我是猫肿么破》轩ZONE X 萧翟：★★★★（16）</summary><div>\n<ul>\n<li>【22.6.25】主角：阚泽 X 司景</li>\n<li>配音和后期十分舒服，特别是司景（CV 萧翟）、白宏礼（CV 倒吊男）、白寻（CV 诺辰），配得很贴又很有趣，都有两幅面孔，司景是拽萌，开头几期放飞自我了，白宏礼是怂萌，最后一个又病娇又萌。声声慢的报幕也很软萌，剧里的攻音还挺茶。</li>\n<li>整体是挺萌的甜饼。中后期有虐的剧情，司景还是条英雄猫。偶尔有幽森的氛围，适合中午下饭听。</li>\n</ul>\n</div></details>\n<details class=\"warning\"><summary>[不更]《被爱妄想症》江笙 X 陈小C（2）</summary><div>\n<ul>\n<li>【22.6.29】主角：秦浪 X 林羡</li>\n<li>又虐了。乍一听是 “今日你对我爱搭不理，来日我让你高攀不起” 的爽文类型，结果是被爱妄想症导致的误会。原来真有这种病。不明上下文的情况下看已更的两期，有点落俗套了。</li>\n<li>冥小鱼声音也好听</li>\n</ul>\n</div></details>\n<details class=\"info\"><summary>《Shawn》商桐X林予曦：★★★★（4）</summary><div>\n<ul>\n<li>【22.6.29】主角：“我” X Shawn</li>\n<li>因为女装和林予曦，被朋友反复安利反复心动 mark。故事的开头挺惊艳的，Shawn 的高跟鞋、旗袍、林予曦的不完全的伪音、叫 “Daddy” 和 “先生” 的声音戳到我心里了。唱的《秦淮景》很惊艳。</li>\n<li>故事有些唏嘘，最开始他可怜 Shawn 和母亲一样的遭遇，怜悯而后爱上 Shawn，Shawn 陪他度过低迷，为他争取机会，他确实让两人过上了好的生活，可 Shawn 的重点是 “和他一起” 过这样的生活。Shawn 挺重情义，被他抛弃就听他安排，意外是为了找他，遗产受益者也是他。而他只在失去时后悔，在事业受挫时才为此伤心（和律师交接是找助手处理的），打着殉情的幌子掩盖他这一生方方面面的失败。前妻 Jennifer 除了眼光不行别的也挺好（CV 黑芝烧声音好听）。</li>\n<li>剧给文锦上添花了，第四期后期很棒。剧末的彩蛋是广播剧福利，把 be 变成 oe 了。但听完还是有些难受。</li>\n</ul>\n</div></details>\n<details class=\"warning\"><summary>[不更]《貌合神离》  楼生 X 陈小C（上期）</summary><div>\n<ul>\n<li>【22.8.18】主角：季明轩 X 沈默</li>\n<li>找了很久，在网友帮助下终于听上了。陈小 C 声音还是挺好听，不过感觉这部剧没有把他的声音用在刀刃上。</li>\n<li>后期略微简陋，只有半期感觉故事还没讲明白（燃兔版三个小时呢）。</li>\n</ul>\n</div></details>\n<details class=\"warning\"><summary>[不更]《折枝·阶下囚 》  燃 X 陈小C（2）</summary><div>\n<ul>\n<li>【22.8.19】主角：段凌 X 陆修文</li>\n<li>困倚危楼原著，半虐半甜，因为转商收回授权，还没来得及甜呢</li>\n<li>15 年的剧，制作后期还有些生涩</li>\n<li>配音：小 C 的声音和选剧都挺合我的胃口的，这部感觉氛围和《活受罪》有点像，但是比起梅梅，会更容易心疼小 C 配出来的角色（是滤镜吧），求而不得，哀而不伤，（外加一点诱），反而是末了燃的哭戏情绪比较浓重一些。斑马配的柳逸也蛮可爱的，虽然菜但讲义气</li>\n<li>看上去倨傲而恃宠而骄，其实是口是心非，非常善良、舍己为人的角色。为他折一枝桃枝，却像是给了他来年的春天。</li>\n</ul>\n</div></details>\n<details class=\"success\"><summary>《艳鬼》昱霖 X 糖醋排骨：★★★☆（3）</summary><div>\n<ul>\n<li>【22.8.21】主角：空华 X 桑陌</li>\n<li>糖醋排骨早期代表作，自己策划的虐剧。公子欢喜原著。人物关系很杂乱，勉强听懂了，两个主役之间的关系是：前世我爱你你却爱着他，我拼命换来的东西你却拱手送给了他，今生你爱我却不说我还以为你还爱着他（略狗血的设定😂）；还有南风、妆妃、华妃、小柔、靳将军、老神仙…… 一共三期，有故事的人物忒多了。</li>\n<li>糖醋排骨早期还是有点清冷的贵气小美人音（想起了叶崇义和雷粤），斑马役的角色仍然有点健气 + 傻乎乎的。</li>\n</ul>\n</div></details>\n<details class=\"success\"><summary>《走狗》商桐 X 逆鳞无伤：★★★（6）</summary><div>\n<ul>\n<li>【22.8.22】主角：陆业征 X 程展心</li>\n<li>原著《走狗》，不过标题跟内容没什么关系。</li>\n<li>弱受，虽然是因为比较惨，但人设还是不讨喜，被治愈后明媚的笑着还是可以的。颇有灰姑娘既视感，主角对金钱也没有概念，一个贫穷的高三生怎么就觉得考上大学的奖学金会有几十万，攻能随便掏 30 万也很恋爱脑。程父从人设上就是个人渣，所以有点为虐而虐了。</li>\n<li>逆鳞无伤的哭戏不错</li>\n</ul>\n</div></details>\n<details class=\"success\"><summary>《岁寒心》天空，苏尚卿：★★★（1）</summary><div>\n<ul>\n<li>【22.8.25】主角：月城苍介，星野淳太</li>\n<li>友情向和风广播剧，时间短角色多，又没有背景简介、故事中交代得不明确、制作又不愿意别人添加字幕，导致故事有些晦涩。主角之间对话稚气。故事设定不错。</li>\n<li>陈想先生役反派雨宫正弘。主角战斗力略弱啊</li>\n</ul>\n</div></details>\n<details class=\"success\"><summary>《雨天的尾巴》天空 X 糖醋排骨：★★★☆（1）</summary><div>\n<ul>\n<li>【22.8.27】主角：展扬羽 X 苗林</li>\n<li>九拉推荐。好爱糖排早期的声音。</li>\n<li>片段的小故事，故事比较动人，讲得也清楚。反转。</li>\n</ul>\n</div></details>\n<details class=\"success\"><summary>《心逾炭火春》紫枫儿 X 天花板：★★★（1）</summary><div>\n<ul>\n<li>【22.8.27】主角：教练 X 总监</li>\n<li>九拉推荐。池袋最强原著。人设弯弯绕绕有些特别。<span class=\"spoiler\" title=\"你知道得太多了\">车</span></li>\n</ul>\n</div></details>\n<details class=\"success\"><summary>《藏娇》贾诩 X 小K：★★★（1）</summary><div>\n<ul>\n<li>【22.8.28】主角：陆北 X 阮珩</li>\n<li>芍药娘原著，小故事。ABO<span class=\"spoiler\" title=\"你知道得太多了\"> 网盘剧</span>。</li>\n<li>受傻傻的，跟他哥卖萌挺可爱的。</li>\n<li>哥哥 cp 擎苍 X 柳凄，说好的番外见结果番外只有主 cp。</li>\n</ul>\n</div></details>\n<details class=\"success\"><summary>《爷们儿》Holynight X 陈小C：★★★☆（全三期）</summary><div>\n<ul>\n<li>【22.9.3】主角：严肆 X 乔已</li>\n<li>静水边原著。女王 C，又是舞蹈教练又是特工的，又美又飒。严肆看起来很霸道其实是很不经撩的忠犬攻。小 C 的美强惨角色又添一员，被组织背叛，把委屈都往肚里咽。林纾也很可怜，爱上极恨的人。</li>\n<li>后期不错</li>\n<li>台词还是比较烫嘴的，外加<span class=\"spoiler\" title=\"你知道得太多了\">有那么一些车</span></li>\n</ul>\n</div></details>\n<details class=\"success\"><summary>《夜会》陈小C，木野信：★★★（全一期）</summary><div>\n<ul>\n<li>【22.9.8】主角：顾欢，顾乐</li>\n<li>小短剧。未能说出口的单向暗恋。</li>\n</ul>\n</div></details>\n<details class=\"success\"><summary>《那个小片警》陈小C X 饕餮：★★★☆（全一期）</summary><div>\n<ul>\n<li>【22.9.9】主角：周一彦 X 乔力</li>\n<li>美人攻，喜欢早期小 C 的泼辣劲儿。周一彦人美心善但是脾气跟炮仗一样一点就着，表明心意时又很温柔，无辜兮兮的，最后是诱攻。</li>\n</ul>\n</div></details>\n<details class=\"success\"><summary>《骑士的情书》擎苍 X 矜持ING：★★★☆（全十期）</summary><div>\n<ul>\n<li>【22.9.10】主角：王齐 X 方士清</li>\n<li>《彼得・潘与辛德瑞拉》里王超的大哥的故事。剧情和《彼得・潘》都有点漫长，十期有点长，分两次听完的。</li>\n<li>刚开始听的时候还是挺惊艳的，矜持 ING 很适合这个角色，有些自卑脆弱犹豫不觉的小美人儿，作作的，容易炸毛，气出攻音。倒吊男的袁瑞也挺喜感的，可怜的娃，傻得可爱。不过这两人的重音确实不太在点上。（小 C 第九期客串了两句柏图，29‘）</li>\n</ul>\n</div></details>\n<details class=\"success\"><summary>《花妖是个坏东西》须王沛 X 陈小C：★★★☆（全一期）</summary><div>\n<ul>\n<li>【22.9.12】主角：柏胥（狼妖） X 花屿（山茶花妖）</li>\n<li>这个花妖，有点智商但不多，有点情商但不多，有点礼貌但不多，语不惊人死不休😂。</li>\n</ul>\n</div></details>\n<details class=\"success\"><summary>79.《一只胡萝卜精》陈小C X Linky：★★★☆（全一期）</summary><div>\n<ul>\n<li>【22.9.12】主角：黄牡丹精 X 胡萝卜精（应该是这样，听的时候站反了）漫改，好像之前还挺火的，去看了，两小只的原身真丑啊，不过还好 C 的声音是美人。</li>\n<li>一路陪跑的黄牡丹，有点小虐，胡萝卜憨憨的。</li>\n</ul>\n</div></details>\n<details class=\"info\"><summary>《两口子的第七年》冬冬 X 乘风归去：★★★★（全三期）</summary><div>\n<ul>\n<li>【22.9.18】主角：孟小园 X 黎海唐</li>\n<li>总结：13、14 年的剧，剧情台词设计得都挺流畅的，后期挺好的，氛围到位。</li>\n<li>剧情：应该是年下，小园有些幼稚但有年轻人的朝气，也很坦诚，（还是个嘤嘤怪老是向老婆撒娇）；海唐被家庭抛弃所以敏感自卑，发现感情淡了就开始别扭了，产生了疏离感。好在一个抵挡得住诱惑（内心 OS：我家海唐比你高比你壮比你好看比你体贴，滤镜开满），一个愿意信任。吴筱山（陈小 C 役）主动、绿茶式温柔、貌美、大长腿，但是强迫不可，还自欺欺人，最后被小园拿开水瓶打了，还被海唐揍了，海唐揍人的时候还挺帅气，一揍把小园的不安给揍散了（CC 的早期反派美人炮灰攻，末了还说：祝你俩白头偕老断子绝孙）。</li>\n<li>角色 &amp; 配音：整体演技挺好，入戏。刚开始有点分不清冬冬和乘风，后面就靠性格区分，一个呆愣直率，一个成熟稳重但内心自卑又不愿意表达（评论区说秦川，现在靠吐词听得出来了，<span class=\"spoiler\" title=\"你知道得太多了\">之前想成朴枫了我的锅</span>）。小 C 配的吴筱山正常的样子还像个人，追求的时候的自信和撩拨，强迫的时候的极度自我，事后对着小园装无辜，对着海唐绿茶，配得好。风雨归舟配的常辞傻兮兮的；陆念 CV Mic 配的弱智小孩，不过挺可爱的；木野信配的弟弟孟小衡，刚开始看着不闻不问的，遇到事很有兄长风范，可靠。夫夫相性问答整得跟真的访谈一样，有种他们真实存在的感觉，小园的 n 次夫唱夫随 “就是，么么哒～”。</li>\n<li>海唐很温柔，给陆念编织了一个梦，梦里他就是自闭症大雄。有海唐这个机器猫，陆念一定能成为一个勇敢的孩子。</li>\n</ul>\n</div></details>\n<details class=\"success\"><summary>《他的礼物》郝凡 X 小狼：★★★（全一期）</summary><div>\n<ul>\n<li>【22.9.20】主角：季钦 X 泽安</li>\n<li>那两年的泽安其实挺好的，替他铺好一切，最后还自责抑郁了很长时间。原本的泽安有些不值，家人又不是不能接受他，朋友不习惯也可以远离，季钦不爱他就分吧，太跟自己较劲了，一定要获得别人的认同，可惜，毁了自己也毁了替身的用心良苦。</li>\n<li>主役声音好听</li>\n</ul>\n</div></details>\n<details class=\"info\"><summary>《营销号说你喜欢我 第一季》DK（役周秋隼）X 冬冬（役司镜若）：★★★★（全十期）</summary><div>\n<ul>\n<li>\n<p>整体配音、导演、后期都挺到位的。很多细节很自然又很让人入戏，人物也比较饱满有特点。不过最后几期收尾略仓促，故事还没讲完，连标题都没切到，配角戏份比较重。</p>\n</li>\n<li>\n<p>最喜欢的是冬冬的声音和戏中戏《烽火》。</p>\n<ul>\n<li>\n<p>很喜欢冬冬的受音，这个角色还比较立体，不是傻白甜，会撒撒娇卖卖萌，但是脑子还比较清醒，看着淡定但内心 OS 有很多委屈 / 搞笑 / 咆哮体之类的。整体演技都挺好，几个小孩儿还真找了小孩来配，戏中戏里冬冬和 DK 的演技忒好了。</p>\n</li>\n<li>\n<p>《烽火》背景是民国时期，逻辑比较顺，be，养兄弟之间的感情很真切，比剧本身更有实感。</p>\n</li>\n</ul>\n</li>\n</ul>\n</div></details>\n<details class=\"success\"><summary>《犹记斐然》弦小雾（役游信） X 朴枫（役季斐然）：★★★（全一期）</summary><div>\n<ul>\n<li>误会。弦小雾声音好听，雅致，朴枫也不错，不过还是没听出来。</li>\n<li>在猫耳没字幕地听完了，剧情没完全 get 到，结果发现 B 站有字幕且弹幕多很多。看了才明白误会在哪里，可是两个人相爱，总不至于一丝痕迹也没有的。</li>\n</ul>\n</div></details>\n",
            "tags": [
                "广播剧",
                "广播剧",
                "整理"
            ]
        },
        {
            "id": "https://sneexy.github.io/2022/08/27/site/%E7%BD%91%E7%AB%99%E8%AE%BE%E7%BD%AE/",
            "url": "https://sneexy.github.io/2022/08/27/site/%E7%BD%91%E7%AB%99%E8%AE%BE%E7%BD%AE/",
            "title": "网站设置",
            "date_published": "2022-08-27T04:16:45.000Z",
            "content_html": "<h1 id=\"常用命令\"><a class=\"anchor\" href=\"#常用命令\">#</a> 常用命令</h1>\n<ul>\n<li>Hexo 命令（<span class=\"exturl\" data-url=\"aHR0cHM6Ly9oZXhvLmlvL3poLWNuLw==\">官网</span>）\n<ul>\n<li>写博客\n<ul>\n<li>hexo new &quot;文件名&quot;</li>\n</ul>\n</li>\n<li>运行\n<ul>\n<li>hexo clean</li>\n<li>hexo g</li>\n<li>hexo server</li>\n<li>hexo d</li>\n</ul>\n</li>\n<li>运行（升级版）\n<ul>\n<li>跑起来：hexo clean &amp;&amp; hexo g &amp;&amp; hexo server</li>\n<li>推上去：hexo clean &amp;&amp; hexo g &amp;&amp; hexo d</li>\n</ul>\n</li>\n</ul>\n</li>\n<li>git 命令（平时 hexo d 就够了）\n<ul>\n<li>git add .</li>\n<li>git commit -m &quot;&quot;</li>\n<li>git push</li>\n</ul>\n</li>\n</ul>\n<h1 id=\"配置\"><a class=\"anchor\" href=\"#配置\">#</a> 配置</h1>\n<ol>\n<li>把内容 git clone 下来， <code>git clone git@github.com:Sneexy/WebsiteContent.git</code></li>\n<li>在项目文件夹 <code>WebsiteContent</code>  下把 shoka（<span class=\"exturl\" data-url=\"aHR0cHM6Ly9naXRodWIuY29tL2FtZWhpbWUvaGV4by10aGVtZS1zaG9rYQ==\">hexo-theme-shoka</span>）拉下来，文件夹名字改为 shoka</li>\n<li><code>npm i hexo-renderer-multi-markdown-it --save --ignore-scripts</code></li>\n<li><code>npm install</code></li>\n</ol>\n<p>环境整坏了时：</p>\n<ol>\n<li>卸载 nodejs：<span class=\"exturl\" data-url=\"aHR0cHM6Ly93d3cuY3Nkbi5uZXQvdGFncy9NdHphUWczc016YzVOelF0WW14dlp3TzBPME9PME8wTy5odG1s\">brew mac 卸载 nodejs - CSDN</span></li>\n<li>重装 nodejs（for npm）：<span class=\"exturl\" data-url=\"aHR0cHM6Ly9ibG9nLmNzZG4ubmV0L3FxXzQwODkxMzIyL2FydGljbGUvZGV0YWlscy8xMDkzMzYyNjY=\">mac 通过 HomeBrew 安装 node.js（自带 npm 包管理器）</span></li>\n</ol>\n<h1 id=\"添加包依赖\"><a class=\"anchor\" href=\"#添加包依赖\">#</a> 添加包依赖</h1>\n<ul>\n<li>\n<p>不知道版本： <code>npm install 包名</code></p>\n</li>\n<li>\n<p>知道版本</p>\n<ul>\n<li><code>package.json</code>  的 <code>dependencies</code>  里按格式添加</li>\n<li><code>npm install</code></li>\n</ul>\n</li>\n</ul>\n<h1 id=\"使用效果\"><a class=\"anchor\" href=\"#使用效果\">#</a> 使用效果</h1>\n<p><span class=\"exturl\" data-url=\"aHR0cHM6Ly9zaG9rYS5sb3N0eXUubWUvY29tcHV0ZXItc2NpZW5jZS9ub3RlL3RoZW1lLXNob2thLWRvYy8=\">Hexo 主题 Shoka &amp; multi-markdown-it 渲染器使用说明</span></p>\n<h2 id=\"添加友链\"><a class=\"anchor\" href=\"#添加友链\">#</a> 添加友链</h2>\n<ol>\n<li>\n<p>在 <code>source/friends</code>  文件夹的 <code>_data.yml</code>  里按照以下格式（<span class=\"exturl\" data-url=\"aHR0cHM6Ly9zaG9rYS5sb3N0eXUubWUvY29tcHV0ZXItc2NpZW5jZS9ub3RlL3RoZW1lLXNob2thLWRvYy9zcGVjaWFsLw==\">项介绍</span>）</p>\n<figure class=\"highlight yml\"><figcaption data-lang=\"YAML\"></figcaption><table><tr><td data-num=\"1\"></td><td><pre><span class=\"token punctuation\">-</span> <span class=\"token key atrule\">site</span><span class=\"token punctuation\">:</span> <span class=\"token comment\">#站点名称</span></pre></td></tr><tr><td data-num=\"2\"></td><td><pre>  <span class=\"token key atrule\">owner</span><span class=\"token punctuation\">:</span> <span class=\"token comment\">#管理员名字</span></pre></td></tr><tr><td data-num=\"3\"></td><td><pre>  <span class=\"token key atrule\">url</span><span class=\"token punctuation\">:</span> <span class=\"token comment\">#站点网址</span></pre></td></tr><tr><td data-num=\"4\"></td><td><pre>  <span class=\"token key atrule\">desc</span><span class=\"token punctuation\">:</span> <span class=\"token comment\">#简短描述</span></pre></td></tr><tr><td data-num=\"5\"></td><td><pre>  <span class=\"token key atrule\">image</span><span class=\"token punctuation\">:</span> <span class=\"token comment\">#一张图片</span></pre></td></tr><tr><td data-num=\"6\"></td><td><pre>  <span class=\"token key atrule\">color</span><span class=\"token punctuation\">:</span> <span class=\"token comment\">#颜色代码</span></pre></td></tr></table></figure></li>\n<li>\n<p>在 <code>source/friends</code>  文件夹的 <code>index.md</code>  里适当地方写上 <code>&#123;% linksfile friends/_data.yml %&#125;</code> 。</p>\n</li>\n</ol>\n<h2 id=\"隐藏文字\"><a class=\"anchor\" href=\"#隐藏文字\">#</a> 隐藏文字</h2>\n<p><span class=\"exturl\" data-url=\"aHR0cHM6Ly9zaG9rYS5sb3N0eXUubWUvY29tcHV0ZXItc2NpZW5jZS9ub3RlL3RoZW1lLXNob2thLWRvYy9zcGVjaWFsLw==\">功能介绍</span></p>\n<p>使用格式（感叹号和文字间不要有空格）（本地不能查看，需要渲染后网站上看）</p>\n<pre><code>!!黑幕黑幕黑幕黑幕黑幕黑幕!!： 鼠标滑过显示内容\n!!模糊模糊模糊模糊模糊模糊!!&#123;.bulr&#125; ： 选中文字显示内容\n</code></pre>\n<h2 id=\"注释\"><a class=\"anchor\" href=\"#注释\">#</a> 注释</h2>\n<figure class=\"highlight markdown\"><figcaption data-lang=\"markdown\"></figcaption><table><tr><td data-num=\"1\"></td><td><pre><span class=\"token url-reference url\"><span class=\"token punctuation\">[</span><span class=\"token variable\">//</span><span class=\"token punctuation\">]</span><span class=\"token punctuation\">:</span> # <span class=\"token string\">(哈哈我是注释，不会在浏览器中显示。)</span></span></pre></td></tr><tr><td data-num=\"2\"></td><td><pre><span class=\"token url-reference url\"><span class=\"token punctuation\">[</span><span class=\"token variable\">^_^</span><span class=\"token punctuation\">]</span><span class=\"token punctuation\">:</span> # <span class=\"token string\">(哈哈我是注释，不会在浏览器中显示。)</span></span></pre></td></tr><tr><td data-num=\"3\"></td><td><pre></pre></td></tr><tr><td data-num=\"4\"></td><td><pre>[^_^]:</pre></td></tr><tr><td data-num=\"5\"></td><td><pre>    commentted-out contents</pre></td></tr><tr><td data-num=\"6\"></td><td><pre>    should be shift to right by four spaces (<span class=\"token code-snippet code keyword\">`>>`</span>).</pre></td></tr></table></figure><p>参考<sup class=\"footnote-ref\"><a href=\"#fn1\" id=\"fnref1\">[1]</a></sup><sup class=\"footnote-ref\"><a href=\"#fn2\" id=\"fnref2\">[2]</a></sup></p>\n<p>注意：这句代码前面要空行。支持多行注释，括号中不要空行</p>\n<hr class=\"footnotes-sep\" />\n<section class=\"footnotes\">\n<ol class=\"footnotes-list\">\n<li id=\"fn1\" class=\"footnote-item\"><p><span class=\"exturl\" data-url=\"aHR0cHM6Ly93d3cuaW1vb2MuY29tL2FydGljbGUvMjM0MDA=\">https://www.imooc.com/article/23400</span> <a href=\"#fnref1\" class=\"footnote-backref\">↩︎</a></p>\n</li>\n<li id=\"fn2\" class=\"footnote-item\"><p><span class=\"exturl\" data-url=\"aHR0cHM6Ly93d3cuamlhbnNodS5jb20vcC85YmU4N2U3ZTE1YmY=\">https://www.jianshu.com/p/9be87e7e15bf</span> <a href=\"#fnref2\" class=\"footnote-backref\">↩︎</a></p>\n</li>\n</ol>\n</section>\n",
            "tags": [
                "网站",
                "工具"
            ]
        },
        {
            "id": "https://sneexy.github.io/2022/08/27/drama/CV/%E9%99%88%E6%83%B3%E5%85%88%E7%94%9F-%E9%99%88%E5%B0%8FC/",
            "url": "https://sneexy.github.io/2022/08/27/drama/CV/%E9%99%88%E6%83%B3%E5%85%88%E7%94%9F-%E9%99%88%E5%B0%8FC/",
            "title": "陈想先生/陈小C",
            "date_published": "2022-08-27T01:24:41.000Z",
            "content_html": "<h1 id=\"陈想先生陈小c\"><a class=\"anchor\" href=\"#陈想先生陈小c\">#</a> 陈想先生 / 陈小 C</h1>\n<p>之前写过一个推荐贴：<span class=\"exturl\" data-url=\"aHR0cHM6Ly93d3cuZG91YmFuLmNvbS9ncm91cC90b3BpYy8yNjU2NDM4MjgvP19pPTE1NzUxNTBxMXVkbll1LDE1NzUyMThxMXVkbll1\">CV 陈小 C / 陈想先生 - 气质美人 (douban.com)</span>。</p>\n<h2 id=\"陈小c的声音总结\"><a class=\"anchor\" href=\"#陈小c的声音总结\">#</a> 陈小 C 的声音总结</h2>\n<p>陈小 C 的声音有玉的质感，温润、干净、气质、高贵、自信的大美人，可以是女王受，虽然是纤细的受音，但可以很有气势。可以执着、腹黑、傲娇、冰冷，也可以天真、沙雕，风骚、闷骚。笑起来和撒娇的时候最让人受不住。</p>\n<p>听过的剧里，他的演技都挺好的，虽然声线有限制，但是情绪很饱满多变，配得很自然。听过的剧里《困流》和《我只要你》角色性格比较立体，演技比较明显。</p>\n<p>选剧也很对我胃口，大部分都挺虐的，就算是 he，也得虐过了再 he。而且还得是从过去，到故事开始，到故事结尾，一直虐。身心都要虐。典型的有《桃魅》。</p>\n<p>很多人分不清他和林予曦，但是在我听来，一个是大家闺秀，一个是小家碧玉，陈小 C 虽然是受音，但攻气十足，高傲自信；林予曦的声音就没什么攻击力，软软糯糯像个小白兔，让人想 rua，发脾气跟撒娇卖萌似的，很多时候角色自卑内省。</p>\n<h2 id=\"声音指路\"><a class=\"anchor\" href=\"#声音指路\">#</a> 声音指路</h2>\n<p><div class=\"links\"><div class=\"item\" title=\"陈想先生\"><span class=\"exturl image\" data-url=\"aHR0cHM6Ly93d3cubWlzc2V2YW4uY29tL3NlaXkvMTE0OQ==\" data-background-image=\"/images/avatar.jpg\"></span>\n          <div class=\"info\">\n          <span class=\"exturl title\" data-url=\"aHR0cHM6Ly93d3cubWlzc2V2YW4uY29tL3NlaXkvMTE0OQ==\">陈想先生-水岸聆音</span>\n          <p class=\"desc\">猫耳FM：剧集&朗读</p>\n          </div></div><div class=\"item\" title=\"周小元宵的槲寄生\"><span class=\"exturl image\" data-url=\"aHR0cHM6Ly9zcGFjZS5iaWxpYmlsaS5jb20vOTYxOTIxMTIvc2VhcmNoL3ZpZGVvP2tleXdvcmQ9JUU5JTk5JTg4JUU2JTgzJUIzJUU1JTg1JTg4JUU3JTk0JTlG\" data-background-image=\"/images/404.png\"></span>\n          <div class=\"info\">\n          <span class=\"exturl title\" data-url=\"aHR0cHM6Ly9zcGFjZS5iaWxpYmlsaS5jb20vOTYxOTIxMTIvc2VhcmNoL3ZpZGVvP2tleXdvcmQ9JUU5JTk5JTg4JUU2JTgzJUIzJUU1JTg1JTg4JUU3JTk0JTlG\">周小元宵的槲寄生</span>\n          <p class=\"desc\">B站-朗读单截</p>\n          </div></div></div></p>\n<ul>\n<li>每周三晚漫播直播</li>\n</ul>\n<h2 id=\"他人信息整理\"><a class=\"anchor\" href=\"#他人信息整理\">#</a> 他人信息整理</h2>\n<ul>\n<li><span class=\"exturl\" data-url=\"aHR0cHM6Ly93ZWliby5jb20vMzYyMTk5OTM3MS9MeG1ZV3VSZ3c=\">2022 直播合集</span></li>\n</ul>\n<h2 id=\"听过的剧时间顺序\"><a class=\"anchor\" href=\"#听过的剧时间顺序\">#</a> 听过的剧（时间顺序）</h2>\n<p>截至 22.8.27</p>\n<p>格式：《标题》声优：评分（期数）</p>\n<ol>\n<li>《困流》阿册 / HolyNightX 陈小 C：★★★★★（5）</li>\n<li>《友谊的小船，说翻就翻》陈小 CX 林予曦：★★★☆（1）</li>\n<li>《我只要你》轩辕靖日 X 陈小 C：★★★★☆（3）</li>\n<li>《桃魅》风允之 X 陈小 C：★★★★☆（4）</li>\n<li>《姑妄听之》轩辕靖日 X 陈小 C：★★★★（1）</li>\n<li>《一个人的绅士》羊仔 X 陈小 C：★★★☆（1）</li>\n<li>《都是赖床惹的祸》陈小 CX 小坠：★★★☆（1）</li>\n<li>《喜欢你》鲨鱼 X 陈小 C：★★★☆（1）</li>\n<li>《未亡人》鲨鱼 X 陈小 C：★★★（1）</li>\n<li>《罂粟》魅影之声 X 陈小 C：★★★★（1）</li>\n<li>《痛感》夙七烈 X 陈小 C：★★★☆（1）</li>\n<li>[不更]《关河令》陈小 CX 矜持 ING：★★★☆（1）</li>\n<li>《你是人间小甜饼》 HolyNight X 陈小 C：★★★（2）</li>\n<li>《年少与妖娆》唱油条 X 陈小 C：★★★★☆（5）</li>\n<li>[不更]《三十而受》阎摩 X 陈小 C：★★★☆（2）</li>\n<li>[不更]《被爱妄想症》江笙 X 陈小 C（2）</li>\n<li>[不更]《折枝 / 阶下囚》燃 X 陈小 C（2）</li>\n<li>《爷们儿》Holynight X 陈小 C：★★★☆（3）</li>\n</ol>\n<h3 id=\"追平\"><a class=\"anchor\" href=\"#追平\">#</a> 追平</h3>\n<ul>\n<li>《二进制》正经太郎 X 陈小 C：★★★★（4）</li>\n<li>《我和替身渣攻恋爱后白月光回来了》续续点灯 X 陈小 C（1）</li>\n<li>《替罪羊》轩辕靖日 X 陈小 C（3 上）</li>\n<li>《满分赝品》皮皮鲨 X 陈想先生（1）</li>\n<li>《溪亭日暮》魅倾 X 陈想先生</li>\n</ul>\n",
            "tags": [
                "广播剧",
                "声优",
                "声优",
                "女王受",
                "美人音"
            ]
        },
        {
            "id": "https://sneexy.github.io/2022/08/26/writing/Hello-World/",
            "url": "https://sneexy.github.io/2022/08/26/writing/Hello-World/",
            "title": "Hello World",
            "date_published": "2022-08-26T14:45:21.000Z",
            "content_html": "<p>感谢大佬 <a href=\"zhaoyangmushiyi.github.io\">@Monochrome</a> 帮忙建站。代码和服务托管在 Github，网站框架为<span class=\"exturl\" data-url=\"aHR0cHM6Ly9oZXhvLmlvL3poLWNuLw==\"> Hexo</span>。</p>\n<p>一直以来的 All in One 的想法终于可以在这里实现了，也不用担心和谐。</p>\n<p>记录一些声优、广播剧、编程相关，也可能出现其他一切。</p>\n<p>暂时使用了小 C 的头像，最近很喜欢小 C (๑・͈ᴗ・͈)。</p>\n",
            "tags": [
                "日志",
                "Hello_World",
                "日志"
            ]
        }
    ]
}